<?xml version="1.0" encoding="utf-8"?>

<i> 
  <chatserver>chat.bilibili.com</chatserver>  
  <chatid>27810777</chatid>  
  <mission>0</mission>  
  <maxlimit>1000</maxlimit>  
  <state>0</state>  
  <real_name>0</real_name>  
  <source>k-v</source>  
  <d p="84.47000,1,25,16777215,1512627297,0,a1e638d,4018961594">琪亚娜生日快乐~</d>  
  <d p="48.66000,1,25,16777215,1512627334,0,43462dcd,4018962432">听出来了，雪狼最后一关的背景音乐</d>  
  <d p="68.94200,1,25,16777215,1512627345,0,803872c3,4018962678">生日快乐</d>  
  <d p="48.17500,1,25,16777215,1512627612,0,7ee8c7,4018968529">琪亚娜生日快乐</d>  
  <d p="10.60300,1,25,16777215,1512627691,0,ba0e3266,4018970270">崩崩崩？？？</d>  
  <d p="184.89900,5,25,14811775,1512627797,0,d69f67a,4018972725">好好听呀!</d>  
  <d p="4.82100,5,25,16777215,1512627923,0,ba0e3266,4018975589">配视频的话代入感会好很多</d>  
  <d p="72.72600,1,25,16777215,1512628002,0,f53cc637,4018977435">= =明明是因为小林唱的才弹得= = 和大伟没关系</d>  
  <d p="95.61700,1,25,16777215,1512628064,0,25cca02f,4018978808">前排前排</d>  
  <d p="141.52200,1,25,16777215,1512628110,0,25cca02f,4018979847">推荐哈农的 你要笑死我 哈哈哈哈哈</d>  
  <d p="193.86400,1,25,16777215,1512628528,0,ff3899e8,4018989104">a叔牛逼</d>  
  <d p="12.17800,5,25,15138834,1512628631,0,bd3de4c5,4018991371">崩崩崩 。。米哈游唱片厂。。。</d>  
  <d p="143.78400,1,18,14811775,1512628453,0,30806a0,4018993713">推荐哈农的那个我给你推荐的老中医</d>  
  <d p="6.30000,1,25,16777215,1512628917,0,7c0bad26,4018997872">哇崩坏和A叔合体了</d>  
  <d p="15.31700,1,25,16777215,1512629276,0,a9293bc3,4019005206">哇哇哇第一次这么前</d>  
  <d p="33.40000,1,25,16777215,1512629400,0,9dfa1ea3,4019007826">A叔好棒啊</d>  
  <d p="25.98400,1,25,16777215,1512629499,0,4e4d6360,4019009988">2小时前</d>  
  <d p="219.60000,1,25,16777215,1512629586,0,9dfa1ea3,4019011908">这个衔接</d>  
  <d p="129.06700,1,25,16777215,1512629643,0,1765f94c,4019013083">前面的，你认真的吗？</d>  
  <d p="116.34000,1,25,16777215,1512630029,0,a2f392d4,4019021421">Kiyana生快</d>  
  <d p="101.90100,1,25,16777215,1512630121,0,414c564e,4019023377">自己品味怪别甩锅给歌我谢谢你</d>  
  <d p="176.58900,1,25,16777215,1512630233,0,414c564e,4019025696">听得好激动灭哈哈哈哈哈</d>  
  <d p="216.58000,1,25,16777215,1512630297,0,414c564e,4019027032">崩坏系列的灵魂之曲！！！赛高啊啊啊啊啊啊</d>  
  <d p="84.32700,1,25,16777215,1512630306,0,b456b671,4019027225">Kiana生日快乐</d>  
  <d p="68.12400,1,25,16777215,1512630619,0,7082fbb5,4019033854">Happy birthday kiana！</d>  
  <d p="116.98800,1,25,16777215,1512630668,0,7082fbb5,4019034827">许愿2nd</d>  
  <d p="20.05600,1,25,16777215,1512631556,0,b9170ee8,4019055361">Kiana生日快乐！</d>  
  <d p="230.59000,1,25,16777215,1512631672,0,9ce96ad0,4019055601">啪啪啪啪啪</d>  
  <d p="82.32200,1,25,16777215,1512631927,0,ec610db9,4019060871">kiana生日快乐！！！！！！</d>  
  <d p="127.43200,1,25,16777215,1512632566,0,907f1dc0,4019074287">为什么叫草履虫……</d>  
  <d p="127.44500,5,25,16777215,1512632645,0,424a7356,4019075878">说练哈农那个认真的嘛，来来来，你去练练a叔其他的曲子</d>  
  <d p="123.22600,1,25,16777215,1512632758,0,f95aa38f,4019078332">崩坏3启动 充值648 扩充补给 山吹 山吹 山吹 山吹 崩坏3卸载</d>  
  <d p="91.68700,1,25,16777215,1512633708,0,74452dda,4019099090">微信见</d>  
  <d p="55.33800,1,25,16777215,1512633728,0,bee09d88,4019099551">齐亚娜生日快了</d>  
  <d p="67.77800,1,25,16777215,1512633741,0,bee09d88,4019099784">许愿月光</d>  
  <d p="169.41100,1,25,16777215,1512633843,0,bee09d88,4019101871">崩坏3一周年</d>  
  <d p="229.23900,1,25,16777215,1512633927,0,a67a1ea6,4019103744">谢谢A叔！琪亚娜生日快乐</d>  
  <d p="33.83900,1,25,16777215,1512634232,0,d79879d9,4019113898">KIANA生日快乐</d>  
  <d p="4.40100,1,25,16777215,1512634322,0,86705a40,4019115625">崩崩崩！</d>  
  <d p="25.02100,1,25,16777215,1512634355,0,86705a40,4019116346">小公主，生日快乐</d>  
  <d p="59.14000,1,25,16777215,1512634409,0,86705a40,4019117579">天，真是崩3，激动⊙∀⊙</d>  
  <d p="149.74100,1,25,16777215,1512634502,0,86705a40,4019119658">哈哈哈哈哈哈哈</d>  
  <d p="20.62200,1,25,16777215,1512634532,0,bf9e8d12,4019120312">话说有点音画不同步</d>  
  <d p="205.56100,1,25,16777215,1512634564,0,86705a40,4019120997">白月光~</d>  
  <d p="226.78100,1,25,16777215,1512634589,0,86705a40,4019121599">超美！</d>  
  <d p="150.39800,1,25,16777215,1512634598,0,eb00a94e,4019121762">推荐哈农你是想笑死我吗(ಡωಡ)</d>  
  <d p="33.14100,1,25,16777215,1512634724,0,3b191f8b,4019124583">刚刚</d>  
  <d p="210.06300,5,25,16707842,1512634466,0,c5bbb940,4019125193">崩坏世界的歌姬ヾ(✿ﾟ▽ﾟ)ノ</d>  
  <d p="113.44000,1,25,16777215,1512634991,0,3cd5310f,4019130835">话说这是哪个场景bgm</d>  
  <d p="6.13400,1,25,16777215,1512635021,0,aea7ce25,4019131084">666666666</d>  
  <d p="169.72800,1,25,16777215,1512634767,0,b1f3fa01,4019131793">好听</d>  
  <d p="166.58500,1,25,16777215,1512635323,0,868097d9,4019138026">音画有点不同步…</d>  
  <d p="67.41400,1,25,16777215,1512635244,0,4bdbbca9,4019138541">kiana生日快乐！</d>  
  <d p="219.31300,1,25,16777215,1512635449,0,380b3470,4019140918">最后鸡皮疙瘩起来了啊啊啊啊！！</d>  
  <d p="46.86700,1,25,16777215,1512635600,0,f6c5052a,4019146770">kiana老婆大人生日快乐</d>  
  <d p="103.25500,1,25,16777215,1512635866,0,8922c8d9,4019150384">琪亚娜生日快乐</d>  
  <d p="100.12800,1,25,16777215,1512637043,0,724b4bc1,4019179151">琪亚娜生日快乐</d>  
  <d p="87.16100,1,25,16777215,1512637194,0,f329003a,4019183004">Kiana生日快乐 A叔赛高</d>  
  <d p="194.54900,1,25,16777215,1512637989,0,9abcb4c6,4019203584">怎么我这里看有点音画不同步...</d>  
  <d p="138.50200,1,25,16777215,1512638106,0,2b3f39f9,4019207305">骑鸭娜是单细胞傻子～草履虫</d>  
  <d p="24.64500,1,25,16777215,1512638222,0,91341d24,4019209926">什么是蹦蹦蹦</d>  
  <d p="41.82400,1,25,16777215,1512638239,0,91341d24,4019210423">什么?是崩崩崩!!</d>  
  <d p="136.73100,1,25,16777215,1512638418,0,ddef1b26,4019215314">同意，感觉A叔瘦了</d>  
  <d p="206.86600,1,25,16777215,1512638447,0,a19dd2b3,4019216104">崩坏世界的歌姬！！！！！</d>  
  <d p="47.64500,1,25,16777215,1512638548,0,e2d62fb4,4019218714">草履虫</d>  
  <d p="79.94800,1,25,16777215,1512638580,0,e2d62fb4,4019219574">大伟哥的海外骗氪计划通</d>  
  <d p="44.85000,1,25,16777215,1512638619,0,8de99da,4019228244">羽生生日快乐!</d>  
  <d p="82.57900,5,25,15138834,1512638898,0,804d6545,4019228575">琪亚娜生日快乐！我的公主</d>  
  <d p="53.69300,5,25,15138834,1512638952,0,8de99da,4019229588">为a叔打call</d>  
  <d p="25.74900,1,25,16777215,1512639331,0,a8e43312,4019240108">前排围观</d>  
  <d p="9.75800,1,25,16777215,1512639643,0,747e2165,4019252152">前前前</d>  
  <d p="30.10500,1,25,16777215,1512639767,0,747e2165,4019252830">开始了</d>  
  <d p="8.52900,1,25,16777215,1512639859,0,1ed14b93,4019255517">从贴吧过来</d>  
  <d p="57.30000,1,25,16777215,1512639908,0,1ed14b93,4019256937">大伟又拆了一个别墅吧</d>  
  <d p="123.47300,1,25,16777215,1512639974,0,1ed14b93,4019258965">草履虫生日快乐</d>  
  <d p="26.04200,1,25,16777215,1512639926,0,10c7bee7,4019260629">手瘦了？错觉吗</d>  
  <d p="73.64400,1,25,16777215,1512640068,0,1ed14b93,4019261633">表示刷火傻碎片听的耳朵出茧</d>  
  <d p="116.20900,1,25,16777215,1512640133,0,415556df,4019263614">前排抱走琪亚娜（赌上节操这个视频能进好多年榜）</d>  
  <d p="26.81300,1,25,16777215,1512640298,0,8d42d51e,4019268568">卧槽卧槽~米...米哈游？！</d>  
  <d p="101.23600,1,25,16777215,1512640372,0,8d42d51e,4019270942">A叔竟然编曲弹这个我实在太鸡冻了</d>  
  <d p="98.38900,1,25,16777215,1512640431,0,fc0f070,4019272627">Kiana,Happy birthday!</d>  
  <d p="201.59100,1,25,16777215,1512640499,0,8d42d51e,4019274678">卧槽，崩坏世界的歌姬~</d>  
  <d p="209.54000,1,25,16777215,1512640507,0,8d42d51e,4019274941">A叔无所不能</d>  
  <d p="70.84300,1,25,16777215,1512640717,0,999b8c69,4019284559">琪亚娜生日快乐</d>  
  <d p="72.61900,4,25,41194,1512640851,0,999b8c69,4019285543">琪亚娜生日快乐</d>  
  <d p="169.38600,1,25,16777215,1512641043,0,f157cc0a,4019291761">慢下来才发现 话音有点不同步？</d>  
  <d p="100.35900,1,25,16777215,1512641314,0,19bb8437,4019301619">Happy Birthday To Kiana！</d>  
  <d p="182.01000,1,25,16777215,1512641065,0,c7332b94,4019302215">渐强好带感</d>  
  <d p="135.38600,1,25,16777215,1512641367,0,19bb8437,4019302855">单细胞</d>  
  <d p="19.83200,1,25,16777215,1512641403,0,572705fc,4019304094">为了崩崩崩进来了</d>  
  <d p="30.25800,1,25,16777215,1512641411,0,39789ce0,4019304486">雅琪娜生日快乐！</d>  
  <d p="101.86700,1,25,16777215,1512641416,0,6a90841d,4019304647">听完单抽出奇迹</d>  
  <d p="45.54100,1,25,16777215,1512641358,0,9613712f,4019306270">Kiana生日快乐！</d>  
  <d p="56.69700,1,25,16777215,1512641585,0,a3d1b7be,4019311172">Kiana生日快乐</d>  
  <d p="192.44700,1,25,15138834,1512641654,0,9613712f,4019312824">A叔玩手游，以前舰c玩的很厉害</d>  
  <d p="29.29300,1,25,16777215,1512641712,0,a7c83224,4019314845">kiana酱生日快乐！</d>  
  <d p="52.29700,5,25,16711680,1512641776,0,a7c83224,4019316987">kiana酱生日快乐！</d>  
  <d p="30.81900,1,25,16777215,1512641870,0,ffff5e5b,4019320179">kiana生日快乐</d>  
  <d p="53.22000,1,25,16777215,1512641862,0,36580fb2,4019320538">老婆大人生日快乐</d>  
  <d p="45.94300,1,25,16777215,1512641990,0,69638146,4019324375">kiana生日快乐！</d>  
  <d p="167.45200,1,25,16777215,1512642008,0,a9293bc3,4019324978">我也觉得很像no game no life</d>  
  <d p="25.38200,1,25,16777215,1512642345,0,1943b745,4019336764">崩崩崩？？？666</d>  
  <d p="206.36900,1,25,16777215,1512642608,0,e2bb6ef5,4019346164">其实到这里我才开始有印象。。</d>  
  <d p="210.86200,1,25,16777215,1512642680,0,8e3e4db9,4019348799">承包圆手指尖</d>  
  <d p="125.62500,1,25,16777215,1512642586,0,373adedb,4019356116">表白</d>  
  <d p="21.72300,1,25,13395711,1512643139,0,156d976b,4019366163">这块好好听！</d>  
  <d p="16.42200,1,25,16777215,1512643387,0,4c22f86a,4019375571">我是第一个？</d>  
  <d p="52.78200,1,25,16777215,1512643433,0,4c22f86a,4019377612">我真的是第一个！</d>  
  <d p="202.68600,1,25,16777215,1512643517,0,1fa5e696,4019380811">音画不同步那是因为你们看到的是残影（滑稽）</d>  
  <d p="110.49000,1,25,16777215,1512643990,0,a7b7be40,4019398493">琪亚娜生日快乐</d>  
  <d p="91.19600,4,25,16777215,1512643823,0,1f1ac6ca,4019402843">火钳刘明！</d>  
  <d p="107.09000,1,25,16777215,1512644141,0,c98e7720,4019404165">beautiful</d>  
  <d p="176.14200,4,25,16711680,1512644165,0,1d098864,4019405044">第一，No game no life前奏也是钢琴，当然会觉得有点像</d>  
  <d p="176.14200,4,25,16711680,1512644242,0,1d098864,4019407973">第二，No game no life主题曲叫做This Game，这点记住好伐。。。</d>  
  <d p="165.86200,1,25,16777215,1512644304,0,72d336a2,4019410261">的确像。</d>  
  <d p="21.89700,1,25,16777215,1512644566,0,64c5a038,4019420005">琪亚娜生快</d>  
  <d p="154.93600,1,25,16777215,1512645478,0,6b0a2c3f,4019454793">耳朵怀孕了要</d>  
  <d p="22.86900,1,25,16777215,1512645387,0,88ad2b55,4019455262">靠前耶</d>  
  <d p="178.95600,1,25,16777215,1512645501,0,6b0a2c3f,4019455664">浑身起鸡皮疙瘩我的妈呀</d>  
  <d p="30.08200,1,25,16777215,1512645816,0,16ec6381,4019468215">手指残影。。。</d>  
  <d p="24.13900,1,25,16777215,1512645923,0,a38abab4,4019472301">壮哉我大崩坏3</d>  
  <d p="79.08800,4,25,13369344,1512646177,0,968d9b03,4019482474">2017 12 07 19：:35 留</d>  
  <d p="3.26300,5,25,41194,1512646407,0,d15f080d,4019491563">哈哈哈前排承包A叔</d>  
  <d p="137.57500,1,25,16777215,1512647046,0,80d37f7b,4019517243">阿湿波bgm</d>  
  <d p="102.47300,1,25,16777215,1512646783,0,47e141b0,4019518113">kiana生日快乐</d>  
  <d p="178.55600,1,25,16777215,1512647109,0,c0c038d2,4019519853">好听诶</d>  
  <d p="19.70000,1,25,16777215,1512647207,0,377ce38b,4019523863">7小时前</d>  
  <d p="25.62000,1,25,15138834,1512647337,0,f638f232,4019529012">kiana生日快乐！</d>  
  <d p="1.70700,1,25,16777215,1512647421,0,414c564e,4019532360">刷好大的鱼的某两个id自重</d>  
  <d p="101.60900,1,25,16777215,1512647261,0,414c564e,4019537409">我特么早就说了钢琴版肯定好听</d>  
  <d p="148.53200,1,25,16777215,1512647575,0,414c564e,4019539318">666666救妈神曲</d>  
  <d p="171.52000,1,25,16777215,1512647627,0,414c564e,4019544816">像个飞机呵呵呵</d>  
  <d p="202.58700,1,25,16777215,1512647764,0,414c564e,4019546104">前方高能预警</d>  
  <d p="76.65900,1,25,16777215,1512648370,0,40ecb2da,4019570038">琪亚娜生日快乐</d>  
  <d p="46.88300,1,25,16777215,1512648535,0,16158b39,4019576325">A叔一定是收了8088水晶的广告费</d>  
  <d p="30.99900,1,25,15138834,1512648758,0,6cf787ab,4019585061">生日快乐！许愿电磁炮！</d>  
  <d p="6.57100,1,25,16777215,1512648821,0,fe7af454,4019591579">哇</d>  
  <d p="20.36200,1,25,16777215,1512649021,0,e49445da,4019595351">崩崩崩</d>  
  <d p="30.34100,1,25,16777215,1512649037,0,3116ed43,4019596053">好听！</d>  
  <d p="40.44200,1,25,16777215,1512649050,0,e49445da,4019596564">草履虫生日快乐</d>  
  <d p="68.72200,1,25,14811775,1512648953,0,6cf787ab,4019596805">琪安娜！生日快乐！</d>  
  <d p="68.96000,1,25,16777215,1512648960,0,a712b68c,4019597106">琪亚娜生日快乐！</d>  
  <d p="71.98100,1,25,16777215,1512649085,0,263b14b2,4019598638">生日快乐</d>  
  <d p="9.65900,1,25,16777215,1512649108,0,a3690994,4019598864">琪亚娜生日快乐</d>  
  <d p="100.14100,1,25,16777215,1512648860,0,263b14b2,4019600279">麻花生日快乐</d>  
  <d p="24.55500,1,25,16777215,1512649268,0,fbb97db,4019604900">过来为A叔打call！！！</d>  
  <d p="85.59200,1,25,16777215,1512649129,0,c499632f,4019610745">琪亚娜生日快乐 舰长爱你呦</d>  
  <d p="193.94100,1,25,16777215,1512649495,0,81ede4ce,4019613952">教练，我想学这个</d>  
  <d p="75.91600,1,25,16777215,1512649520,0,c6aa1f26,4019614967">生日快乐！Kiana！Sakamoto留。</d>  
  <d p="1.05900,1,25,16777215,1512649546,0,81ede4ce,4019615966">a叔牛逼</d>  
  <d p="21.22200,1,25,16777215,1512649563,0,d2a0d93,4019616604">突然想公开处崩友2333......ID18231211</d>  
  <d p="70.53200,1,25,16777215,1512649587,0,12a69929,4019617541">琪亚娜公主殿下生日快乐！！！万岁！！！</d>  
  <d p="0.44000,1,25,16777215,1512649642,0,d2a0d93,4019619757">突然想公开处崩友2333。。。ID18231211</d>  
  <d p="97.64300,1,25,16777215,1512649656,0,be876384,4019620286">kiana，生日快乐，一定要和芽衣走到最后啊</d>  
  <d p="195.34100,1,25,6737151,1512649656,0,c6aa1f26,4019620331">蓝色如你眼眸，我永远爱你Kiana！</d>  
  <d p="219.77900,1,25,16777215,1512649687,0,38645a6d,4019621575">纪念我们逝去的崩坏2</d>  
  <d p="10.00000,1,25,16777215,1512649903,0,2c0f4ce7,4019630130">小公主生日快乐</d>  
  <d p="33.76600,1,25,16777215,1512649938,0,94063d6,4019631510">太棒了wwww</d>  
  <d p="227.25100,1,25,16777215,1512649994,0,31a13e83,4019633775">崩坏世界的歌姬。这段超美</d>  
  <d p="70.07000,1,25,16777215,1512650010,0,d0e0b8ce,4019635108">许愿次元!</d>  
  <d p="27.94300,1,25,16777215,1512650077,0,1c040b5c,4019637071">Ich Liebe Dich！！！</d>  
  <d p="33.74100,1,25,16707842,1512650098,0,1c040b5c,4019637863">Ich Liebe Dich</d>  
  <d p="4.69300,1,25,41194,1512650335,0,7d44b55e,4019647136">祝老婆大人生日快乐！</d>  
  <d p="80.70700,1,25,16777215,1512650066,0,c6765fc6,4019647802">大伟日常拆墙</d>  
  <d p="7.43300,1,25,41194,1512650342,0,7d44b55e,4019648170">kiana公主生日快乐</d>  
  <d p="77.74200,1,25,16777215,1512650306,0,91e7ac31,4019650244">kiana生日快乐</d>  
  <d p="23.29600,1,25,16777215,1512650412,0,7d44b55e,4019650371">琪亚娜生日快乐</d>  
  <d p="145.59100,1,25,16777215,1512650451,0,9943941,4019652052">Kiana お誕生日おめでとう</d>  
  <d p="75.00800,1,25,16777215,1512650473,0,7d44b55e,4019652905">琪亚娜生日快乐</d>  
  <d p="13.40000,1,25,16777215,1512650582,0,59608a12,4019657437">鱼，好大的鱼（手动滑稽）</d>  
  <d p="193.63200,1,25,16777215,1512650608,0,7d44b55e,4019658505">前方高能</d>  
  <d p="194.56000,1,25,16777215,1512650594,0,7d44b55e,4019658668">前方高能</d>  
  <d p="198.58000,1,25,16777215,1512650624,0,7d44b55e,4019659143">前方核能</d>  
  <d p="55.62700,1,25,16777215,1512650699,0,3b7d709e,4019662148">kianna生日快乐</d>  
  <d p="98.81200,5,25,3407871,1512650784,0,9eeb70c2,4019665560">琪亚娜生日快乐！</d>  
  <d p="96.20600,1,25,16777215,1512650787,0,6e15d4ab,4019665661">kiana生日快乐</d>  
  <d p="18.36200,1,25,16777215,1512650803,0,4f17f253,4019666299">琪亚娜生日快乐！！！</d>  
  <d p="34.59300,1,25,16777215,1512651073,0,280f5ca,4019677147">kiana生日快乐！</d>  
  <d p="0.00000,1,25,16777215,1512651094,0,bd6ff4c,4019678018">后排</d>  
  <d p="66.12300,1,25,16777215,1512651312,0,40ee4664,4019687019">Kiana生日快乐</d>  
  <d p="71.82000,1,25,16777215,1512651122,0,7d82520e,4019690923">琪安娜生日快乐</d>  
  <d p="66.52000,1,25,16777215,1512651794,0,a211a780,4019707142">琪亚娜生日快乐</d>  
  <d p="22.38500,1,25,16777215,1512651839,0,605aa5a9,4019708997">666</d>  
  <d p="123.29100,1,25,16777215,1512651851,0,234cc73b,4019709525">Kiana生日快乐！</d>  
  <d p="47.00100,1,25,16777215,1512651856,0,cc9f35b0,4019709745">kiana，happy birthday to you！:)</d>  
  <d p="6.60200,1,25,16777215,1512651909,0,ee79334b,4019713113">Ich★Liebe★Dich！</d>  
  <d p="51.04300,1,25,16777215,1512651914,0,448ea03,4019713325">a叔是即兴的……</d>  
  <d p="46.74100,1,25,16777215,1512651953,0,7c573c06,4019714916">琪亚娜生日快乐！</d>  
  <d p="72.90400,1,25,16777215,1512652246,0,5565887f,4019726857">稽亚娜生日快乐</d>  
  <d p="33.41900,1,25,16777215,1512652378,0,7b604003,4019732322">琪亚娜生日快乐！！！！！！！疯狂打电话！！！！！！</d>  
  <d p="205.74300,1,25,16777215,1512652397,0,5565887f,4019733061">崩坏世界的歌姬</d>  
  <d p="53.22000,1,25,16777215,1512652473,0,f513253a,4019736866">happy birthday to kiana</d>  
  <d p="68.15600,1,25,16777215,1512652498,0,1bc6c3d,4019737161">6666</d>  
  <d p="78.66100,1,25,16777215,1512652396,0,4bda4b95,4019744747">琪亚娜生日快乐</d>  
  <d p="76.31500,1,25,16777215,1512652787,0,aeb11bf0,4019749125">我要这硬币有何用</d>  
  <d p="17.20300,1,25,16777215,1512652670,0,12ef50f3,4019756056">公主生快</d>  
  <d p="167.43600,1,25,16777215,1512652731,0,1f613e57,4019758591">草履虫生日快乐????</d>  
  <d p="43.74000,1,25,16777215,1512653058,0,cb3c0100,4019760422">琪亚娜，生日快乐????????！</d>  
  <d p="66.59700,1,25,16777215,1512653090,0,abde63c1,4019761665">琪亚娜生日快乐</d>  
  <d p="39.38000,1,25,16777215,1512653220,0,6bca635f,4019767136">kiana，生日快乐</d>  
  <d p="46.01900,1,25,16777215,1512653381,0,69a1d6d4,4019773893">突然好想学钢琴。。</d>  
  <d p="83.01900,1,25,16777215,1512653430,0,69a1d6d4,4019775970">生日快乐！琪亚娜</d>  
  <d p="227.24300,1,25,16777215,1512653571,0,ba08adc3,4019781851">哇塞鼓掌</d>  
  <d p="76.20100,1,25,16777215,1512653475,0,3202d618,4019782226">想听现场……</d>  
  <d p="30.02100,5,25,41194,1512653295,0,f7eef698,4019782235">琪亚娜生日快乐※</d>  
  <d p="29.27800,1,25,16777215,1512653618,0,9bf0be7f,4019784640">Kiana生日快乐</d>  
  <d p="120.64100,1,25,16777215,1512653538,0,3202d618,4019784920">打那个双子巨大崩坏兽的bgm</d>  
  <d p="25.93200,1,25,16777215,1512653388,0,753497d0,4019786191">马克一哈</d>  
  <d p="38.32100,1,25,16777215,1512653871,0,2b88950e,4019794641">kiana生日快乐！！！</d>  
  <d p="86.74200,5,25,16777215,1512653873,0,c90e0053,4019794761">琪亚娜生日快乐</d>  
  <d p="89.96600,5,25,16777215,1512653883,0,c90e0053,4019795121">琪亚娜生日快乐</d>  
  <d p="92.41600,5,25,16777215,1512653889,0,c90e0053,4019795434">琪亚娜生日快乐</d>  
  <d p="94.23700,5,25,16777215,1512653609,0,c90e0053,4019795653">琪亚娜生日快乐</d>  
  <d p="94.80500,5,25,16777215,1512653899,0,c90e0053,4019795861">琪亚娜生日快乐</d>  
  <d p="95.50000,5,25,16777215,1512653905,0,c90e0053,4019796338">琪亚娜生日快乐</d>  
  <d p="96.17800,5,25,16777215,1512653912,0,c90e0053,4019796656">琪亚娜生日快乐</d>  
  <d p="84.79900,1,25,16777215,1512653947,0,f1fa6cab,4019798191">kiana生日快乐</d>  
  <d p="41.58100,1,25,16777215,1512653988,0,9a87346c,4019800015">许愿 白骑士月光</d>  
  <d p="108.06000,1,25,16777215,1512653995,0,32f88f1c,4019800253">好听～</d>  
  <d p="117.40100,5,25,16777215,1512654237,0,9aae394e,4019810591">听完单抽妖刀๑乛◡乛๑</d>  
  <d p="30.12300,1,25,16777215,1512654329,0,e2f16816,4019814658">琪亚娜生日快乐！！！！！！！！</d>  
  <d p="125.00700,1,25,16777215,1512654358,0,31fe86f7,4019815956">草履虫生快。</d>  
  <d p="45.26500,1,25,16777215,1512654477,0,e65f97ca,4019821164">kiana生日快乐</d>  
  <d p="163.02200,5,25,16776960,1512654495,0,38991fe5,4019821965">还真TM有点像，鱼，好大的鱼，虎纹鲨鱼</d>  
  <d p="63.72200,1,25,16777215,1512654528,0,3f609873,4019823372">月光游侠圣女白练生日快乐！！！！！！！！</d>  
  <d p="28.84200,1,25,16777215,1512654502,0,a902dd09,4019826767">好想是打阿湿波的BGM诶*罒▽罒*</d>  
  <d p="70.41000,1,25,16777215,1512654607,0,ada2a149,4019826838">????傻娜生日快乐????</d>  
  <d p="31.68300,5,25,41194,1512654629,0,c0e1ea0d,4019828621">大伟有钱就是厉害啊</d>  
  <d p="173.22700,5,25,16707842,1512654675,0,24fe0115,4019829801">Ich ★ Liebe ★ Dich</d>  
  <d p="198.07700,1,25,16777215,1512654529,0,c6411a3a,4019835926">生日快乐！</d>  
  <d p="169.44800,1,25,16777215,1512654843,0,9d83f1db,4019837159">好听</d>  
  <d p="161.84200,1,25,16777215,1512654863,0,ce90bc78,4019838007">琪安娜生日快乐</d>  
  <d p="155.06000,1,25,16777215,1512654710,0,72691a19,4019843702">超好听好听！</d>  
  <d p="54.24200,1,25,16777215,1512654808,0,634e109,4019848057">琪亚娜生日快乐</d>  
  <d p="91.71500,1,25,16777215,1512655101,0,d785a7d9,4019848381">生日快乐</d>  
  <d p="127.40100,1,25,16777215,1512655113,0,499368cb,4019848945">打阿湿波的音乐</d>  
  <d p="32.73000,1,25,16777215,1512655010,0,c2299aef,4019849019">kiana 生日快乐</d>  
  <d p="67.06700,1,25,16777215,1512655051,0,c2299aef,4019850837">微信推送………</d>  
  <d p="225.65000,1,25,16777215,1512655221,0,48a07b6d,4019853759">琪亚娜生日快乐</d>  
  <d p="9.88500,1,25,16777215,1512655277,0,6a3f9df,4019856325">微信来的</d>  
  <d p="49.80700,1,25,16777215,1512655315,0,8f6181f4,4019858125">Kiana生日快乐！！！</d>  
  <d p="11.04900,1,25,16777215,1512655384,0,b076d5a4,4019861374">6666</d>  
  <d p="32.90300,1,25,16777215,1512655433,0,ed24ac22,4019863632">2333</d>  
  <d p="0.00000,1,25,16777215,1512655465,0,c6a3cefd,4019865045">为崩崩崩打call</d>  
  <d p="6.38000,1,25,16777215,1512655481,0,8b81ad59,4019865849">我的妈</d>  
  <d p="46.90000,1,25,16777215,1512655451,0,3189d2b7,4019869198">琪亚娜生日快乐</d>  
  <d p="165.52500,5,25,16777215,1512655641,0,8b81ad59,4019873147">前排占领A叔</d>  
  <d p="51.56000,1,25,16777215,1512655674,0,bedd7179,4019874800">德莉莎世界第一可爱</d>  
  <d p="200.34400,1,25,16777215,1512655675,0,8b81ad59,4019874827">前方高能</d>  
  <d p="21.00000,1,25,16777215,1512655751,0,4183e6f5,4019878452">为A叔和崩坏3疯了打call琪亚娜生日快乐！</d>  
  <d p="25.61900,1,25,16777215,1512655792,0,29cb0b67,4019880371">Ich liebe dichKiana</d>  
  <d p="14.84300,1,25,16777215,1512655823,0,46da5f8f,4019881813">琪亚娜生日快乐</d>  
  <d p="40.83200,1,25,16777215,1512655939,0,7cf6897b,4019887214">琪亚娜生日快乐</d>  
  <d p="57.45900,1,25,16777215,1512655968,0,1d6922f0,4019893395">Kiana kaslana,Ich liebe dich.</d>  
  <d p="37.41900,1,25,14811775,1512656317,0,6daadb5c,4019904766">Kiana生日快乐！</d>  
  <d p="68.85000,1,25,16777215,1512656318,0,76bfe6b0,4019904842">琪亚娜生日快乐</d>  
  <d p="13.75500,1,25,16777215,1512656433,0,d91171c8,4019910281">6666666666</d>  
  <d p="37.94100,1,25,16777215,1512656603,0,23e6a1d6,4019918178">琪亚娜生日快乐</d>  
  <d p="213.14500,1,25,16777215,1512656632,0,d91171c8,4019919561">卧槽</d>  
  <d p="14.02000,1,25,15138834,1512656743,0,e4c15367,4019924667">许愿妖刀</d>  
  <d p="19.24000,1,25,15138834,1512656760,0,e4c15367,4019925486">琪亚娜生日快乐！！！</d>  
  <d p="192.55900,1,25,16777215,1512656489,0,23e6a1d6,4019926143">前方高能</d>  
  <d p="84.03300,1,25,16777215,1512656859,0,3e9d498,4019930124">蹦蹦蹦万古长存~~~~~~~</d>  
  <d p="69.35900,1,25,16777215,1512656867,0,3942fb41,4019930515">kiana生日快乐</d>  
  <d p="6.93600,1,25,16777215,1512656886,0,ebe56ba8,4019936305">kiana小公主生日快乐</d>  
  <d p="28.61900,1,25,16777215,1512657093,0,5372447e,4019941212">kiana 生日快乐</d>  
  <d p="121.05900,1,25,16777215,1512657175,0,541a1184,4019945018">kiyana生日快乐????</d>  
  <d p="49.09900,1,25,41194,1512657181,0,4b9ccd65,4019945249">琪亚娜生日快乐</d>  
  <d p="71.54000,1,25,16777215,1512657088,0,e1407b21,4019945744">琪亚娜生日快乐</d>  
  <d p="42.64000,1,25,16777215,1512657176,0,6fe2b0e7,4019945833">完了完了，我听不出来哪首歌，是不是聋了？</d>  
  <d p="15.80100,1,25,16777215,1512657206,0,13835a51,4019946382">失踪人口回归</d>  
  <d p="3.23100,1,25,16777215,1512657247,0,fa7970ca,4019948289">琪亚娜生日快乐*٩(๑´∀`๑)ง*</d>  
  <d p="33.86000,1,25,16777215,1512657247,0,9a997eba,4019948319">老婆生日快乐</d>  
  <d p="101.67000,1,25,16777215,1512657262,0,9706f84c,4019949094">草履虫生日快乐～</d>  
  <d p="34.71100,1,25,16777215,1512657281,0,fa7970ca,4019949930">琪亚娜生日快乐*٩(๑´∀`๑)ง*</d>  
  <d p="75.21800,1,25,16777215,1512657300,0,50dc944f,4019950886">Kiana生日快乐</d>  
  <d p="78.37900,1,25,16777215,1512657324,0,811fe012,4019952032">琪亚娜生日快乐</d>  
  <d p="227.23100,1,25,16777215,1512657477,0,fa7970ca,4019959155">琪亚娜生日快乐*٩(๑´∀`๑)ง*</d>  
  <d p="112.38500,1,25,16777215,1512657467,0,fa7970ca,4019959471">琪亚娜生日快乐*٩(๑´∀`๑)ง*</d>  
  <d p="162.78000,1,25,16777215,1512657498,0,fa7970ca,4019960120">琪亚娜生日快乐*٩(๑´∀`๑)ง*</d>  
  <d p="72.27800,1,25,16777215,1512657508,0,fa7970ca,4019960568">琪亚娜生日快乐*٩(๑´∀`๑)ง*</d>  
  <d p="98.03700,1,25,16777215,1512657885,0,d2369fb,4019978045">生日快乐</d>  
  <d p="4.90100,1,25,16777215,1512658086,0,c6ba7e2,4019988403">琪亚娜生日快乐</d>  
  <d p="76.78000,1,25,16777215,1512658113,0,eed0db40,4019989902">生日快乐kiana.</d>  
  <d p="12.14100,1,25,15138834,1512658189,0,f6c1cbe4,4019993756">Kiana老婆生日快乐</d>  
  <d p="29.10100,1,25,16707842,1512658285,0,fc16137c,4019999432">公主生日快乐</d>  
  <d p="18.80600,1,25,16777215,1512658883,0,e1ab7717,4020027532">琪亚娜生日快乐</d>  
  <d p="6.61700,1,25,16777215,1512658939,0,51434c4a,4020031047">琪安娜生日快乐</d>  
  <d p="53.53200,1,25,16777215,1512658957,0,6e0ce925,4020031114">琪亚娜生日快乐</d>  
  <d p="91.32000,1,25,8700107,1512658955,0,db0389e8,4020031820">琪亚娜生日快乐</d>  
  <d p="54.07600,1,25,16777215,1512658999,0,ee89cef2,4020033020">q</d>  
  <d p="104.03100,1,25,16777215,1512659047,0,7c2d9979,4020035272">琪亚娜生日快乐！</d>  
  <d p="73.81300,1,25,16777215,1512659180,0,59ee23bf,4020041437">琪亚纳生日快乐</d>  
  <d p="8.37900,1,25,41194,1512659226,0,127db933,4020043535">琪亚娜生日快乐✺◟(∗❛ัᴗ❛ั∗)◞✺</d>  
  <d p="169.20700,1,25,16777215,1512659268,0,3a5d9c3f,4020045520">琪亚娜生日快乐~~</d>  
  <d p="24.30800,1,25,16777215,1512659326,0,c364e6eb,4020048176">琪亚娜生日快乐！</d>  
  <d p="180.00100,1,25,16777215,1512659547,0,4f8c38e,4020058435">简直神了</d>  
  <d p="180.42900,1,25,16777215,1512659632,0,b56ba2f8,4020062406">琪亚娜生日快乐~~</d>  
  <d p="20.34300,1,25,16777215,1512659645,0,44bd3748,4020062986">kiana生日快乐</d>  
  <d p="2.40100,1,25,16777215,1512659650,0,d148df3b,4020063177">为a叔打call！</d>  
  <d p="54.68800,1,25,16777215,1512659788,0,1a0b5c4b,4020069428">琪亚娜生日快乐，许愿月光</d>  
  <d p="188.15400,1,25,16777215,1512659899,0,2de8ecde,4020074371">阿湿波镇魂曲</d>  
  <d p="73.80600,1,25,16777215,1512659962,0,f3097a1a,4020077315">Kiana生日快乐！！</d>  
  <d p="194.45900,5,25,16777215,1512660019,0,264692,4020079983">前方高能</d>  
  <d p="112.03300,1,25,16777215,1512660101,0,659a984c,4020083573">琪安娜生日快乐啊</d>  
  <d p="69.28300,1,25,16777215,1512660135,0,153bf973,4020085848">kiana生日快乐！</d>  
  <d p="72.88900,1,25,16777215,1512660178,0,6fe8eaba,4020086932">琪亚娜生日快乐????</d>  
  <d p="78.92200,1,25,16777215,1512660200,0,153bf973,4020087952">kiana生日快乐，保佑我up外出泳装中和百手</d>  
  <d p="74.75200,1,25,16777215,1512660118,0,7292107c,4020088882">生日快乐</d>  
  <d p="83.71200,1,25,16777215,1512660235,0,7292107c,4020089598">生日快乐</d>  
  <d p="64.44500,1,25,16777215,1512660502,0,222a1e27,4020101464">好听</d>  
  <d p="209.96400,1,25,16777215,1512660668,0,222a1e27,4020108792">崩坏世界的歌姬！！！</d>  
  <d p="2.62000,1,25,16777215,1512660878,0,bea184a1,4020117656">许愿一波明天的电磁！</d>  
  <d p="85.18900,1,25,16777215,1512660878,0,84fdec05,4020117710">起亚那</d>  
  <d p="16.08000,1,25,16777215,1512660613,0,bea184a1,4020118551">琪亚娜生日快乐！</d>  
  <d p="86.46900,5,25,16777215,1512660614,0,84fdec05,4020118561">琪亚娜生日快乐！！</d>  
  <d p="41.57900,1,25,16777215,1512661217,0,d3812613,4020131327">琪安娜生日快乐!(^O^)y</d>  
  <d p="33.06800,1,25,16777215,1512661529,0,aa2e098d,4020144007">手速惊人</d>  
  <d p="12.40000,1,25,16777215,1512661603,0,6c3e051c,4020147053">火钳刘明</d>  
  <d p="49.85400,1,25,16777215,1512661981,0,ae15cd1d,4020162546">kiana生日快乐????????????</d>  
  <d p="121.82100,1,25,16777215,1512661901,0,66ec50aa,4020163486">琪亚娜生日快乐！</d>  
  <d p="20.11100,1,25,16777215,1512662086,0,e920e246,4020167310">有谱吗</d>  
  <d p="143.69900,1,25,16777215,1512662233,0,8abf1cfd,4020172160">阿湿波处刑曲</d>  
  <d p="27.10100,1,25,16777215,1512662373,0,e3d0e8a8,4020177447">火钳刘明</d>  
  <d p="46.52600,1,25,16777215,1512662432,0,e3d0e8a8,4020179733">Kiana生日快乐</d>  
  <d p="74.08300,1,25,16777215,1512662450,0,e8b13d3d,4020181140">许愿月光</d>  
  <d p="144.45800,1,25,16777215,1512662582,0,c011ff82,4020185531">真好听～～</d>  
  <d p="48.76600,1,25,16777215,1512662671,0,e34f093c,4020188906">kiana生日快乐</d>  
  <d p="163.62600,1,25,16777215,1512662508,0,e34f093c,4020193225">kiana生日快乐</d>  
  <d p="200.64200,1,25,16777215,1512662830,0,27770595,4020194531">感觉A叔手瘦了，能看到比较明显的棱角了</d>  
  <d p="19.71100,1,25,16777215,1512662555,0,be403723,4020194855">许愿圣光</d>  
  <d p="22.35700,1,25,16777215,1512662846,0,be403723,4020195097">月光</d>  
  <d p="229.40600,1,25,16777215,1512662859,0,e34f093c,4020195562">kiana生日快乐</d>  
  <d p="77.61100,1,25,16777215,1512663264,0,fd1fb198,4020209840">kiana生日快乐!</d>  
  <d p="74.04800,1,25,16777215,1512663434,0,88294816,4020215836">kiana生日快乐！</d>  
  <d p="63.66900,1,25,16777215,1512663572,0,ce6c8451,4020221329">Kiana生日快乐</d>  
  <d p="33.72800,1,25,41194,1512663743,0,fbab7594,4020226961">琪亚娜生日快乐！！！</d>  
  <d p="189.50100,1,25,16777215,1512663899,0,6386cebf,4020231930">岳父大人的女儿生日快乐！</d>  
  <d p="72.01900,5,25,16707842,1512663928,0,3244b9c3,4020232279">琪亚娜生日快乐，陪我一年了我的月光</d>  
  <d p="164.70100,5,25,9487136,1512664119,0,96cdbf4d,4020241579">同感↑</d>  
  <d p="12.52600,1,25,16777215,1512664248,0,f6c1cbe4,4020242322">老婆生日快乐</d>  
  <d p="57.32900,1,25,16777215,1512664241,0,3df4bc56,4020242696">好有感觉！</d>  
  <d p="168.38900,5,25,9487136,1512664279,0,96cdbf4d,4020243308">只是说像了而已，你说这话。。。素质那</d>  
  <d p="48.77200,1,25,16707842,1512664293,0,f6c1cbe4,4020243743">生日快乐！！！！！！！</d>  
  <d p="89.96600,1,25,16777215,1512664367,0,f6c1cbe4,4020245996">Kiana生日快乐！！！！（放下八重樱）</d>  
  <d p="123.20400,1,25,16777215,1512664300,0,f6c1cbe4,4020247115">同求</d>  
  <d p="189.87000,1,25,16777215,1512664516,0,f6c1cbe4,4020250370">Kiana生日快乐</d>  
  <d p="190.57400,1,25,16777215,1512664529,0,f6c1cbe4,4020250754">Kiana生日快乐</d>  
  <d p="0.97500,4,25,11890,1512664534,0,d737dc5b,4020250916">ME社全体祝Kiana生快——索尔（¯﹃¯）</d>  
  <d p="192.38800,1,25,16777215,1512664546,0,f6c1cbe4,4020251286">Kiana生日快乐</d>  
  <d p="228.01400,1,25,16777215,1512664589,0,f6c1cbe4,4020252568">听哭了</d>  
  <d p="45.00100,1,25,16777215,1512664641,0,f32bca56,4020254121">琪亚娜生日快乐！</d>  
  <d p="91.03700,1,25,16777215,1512664724,0,a2f10686,4020256425">草履虫生日快乐</d>  
  <d p="191.49100,1,25,16777215,1512664539,0,f6c1cbe4,4020259197">我也就听了50多遍而已</d>  
  <d p="41.85900,1,25,16777215,1512665218,0,6080346d,4020269620">许愿月光</d>  
  <d p="60.27200,1,25,16777215,1512665708,0,b35516d7,4020281906">蜗矮腻</d>  
  <d p="94.39600,1,25,16777215,1512665984,0,e760c3c,4020288214">琪亚娜，生日快乐！_(:з」∠)_！！</d>  
  <d p="125.01300,1,25,16777215,1512666038,0,1108a3fb,4020289910">666</d>  
  <d p="34.74300,1,25,16777215,1512665800,0,6321b70e,4020290604">kiana 生日快乐！</d>  
  <d p="66.29800,1,25,16777215,1512666640,0,69ad16dc,4020302999">kiana酱生日快乐</d>  
  <d p="70.90200,1,25,16777215,1512666971,0,ff59be86,4020312326">生日快乐Kiana</d>  
  <d p="228.99800,1,25,16777215,1512667090,0,d62f2310,4020312608">崩坏世界的歌姬！！！</d>  
  <d p="23.44000,1,25,16777215,1512667719,0,d902a43a,4020324664">琪亚娜，生日快乐！！</d>  
  <d p="105.09900,1,25,16777215,1512668038,0,478c197b,4020329977">我也来留名</d>  
  <d p="69.63400,1,25,16777215,1512668232,0,648dfe37,4020334846">kiana生日快乐！</d>  
  <d p="23.16100,1,25,16777215,1512668680,0,83204727,4020340175">琪亚娜生日快乐</d>  
  <d p="5.20800,1,25,16777215,1512669044,0,6e47a89a,4020345579">琪亚娜生日快乐！</d>  
  <d p="97.26600,1,25,16777215,1512670975,0,e1c10857,4020369899">！！崩坏</d>  
  <d p="232.16500,1,25,16777215,1512671492,0,443035ae,4020375349">我家琪亚娜生日快乐</d>  
  <d p="180.06900,1,25,16777215,1512671417,0,443035ae,4020375670">祝我家琪亚娜生日快乐</d>  
  <d p="10.75800,1,25,16777215,1512672189,0,c71430ad,4020382076">不玩崩3</d>  
  <d p="123.25700,1,25,16777215,1512673916,0,1d81364b,4020396024">这个手速........</d>  
  <d p="183.61900,1,25,16777215,1512680749,0,b72a3219,4020431338">吓得我又打了遍阿湿波。。。</d>  
  <d p="8.92600,1,25,16777215,1512685038,0,ea311afc,4020446448">我看到了什么！</d>  
  <d p="59.58100,1,25,16777215,1512686844,0,32c19b94,4020454766">Kiana生日快乐！</d>  
  <d p="208.66100,1,25,14811775,1512687109,0,32c19b94,4020455523">崩坏世界的歌姬！</d>  
  <d p="40.36100,1,25,16777215,1512687179,0,ebec43c0,4020455872">kiana生日快乐</d>  
  <d p="116.62100,1,25,16777215,1512687263,0,ebec43c0,4020456271">a叔赛高</d>  
  <d p="159.90200,1,25,16777215,1512687314,0,ebec43c0,4020456518">不是卡农么</d>  
  <d p="11.42100,1,25,16777215,1512687490,0,34942f1,4020457494">琪亚娜生日快乐</d>  
  <d p="13.27400,1,25,16777215,1512688838,0,14d3f8da,4020464391">19小时前</d>  
  <d p="88.80900,1,25,16777215,1512690057,0,2fe13a66,4020471748">琪亚娜生日快乐</d>  
  <d p="40.65500,1,25,16777215,1512692274,0,103b41da,4020488972">Kiana生快</d>  
  <d p="204.22100,1,25,16777215,1512692531,0,f1744be4,4020491283">琪亚娜生日快乐！</d>  
  <d p="99.12200,1,25,16777215,1512694575,0,cb3c0100,4020513899">听着听着就泪目了</d>  
  <d p="5.62000,1,25,16777215,1512694919,0,2fc78cda,4020519366">许愿月光！百手巨人！</d>  
  <d p="69.20800,1,25,16777215,1512698515,0,b46fda44,4020568234">琪亚娜生快</d>  
  <d p="218.66900,1,25,16777215,1512698937,0,9a683683,4020575810">挖槽！！！崩2的曲子！！</d>  
  <d p="40.20300,1,25,16777215,1512699050,0,414c564e,4020577826">这一段旋律贼美</d>  
  <d p="163.42500,1,25,16777215,1512699194,0,414c564e,4020580360">这里越听越燃是肿么肥四！！！</d>  
  <d p="72.55100,1,25,16777215,1512701224,0,687e9c1f,4020618837">虎纹鲨鱼的 233333</d>  
  <d p="60.48900,1,25,16777215,1512702842,0,4d132d35,4020650214">80级萌新许愿月光</d>  
  <d p="8.35100,1,25,16777215,1512703754,0,4dfe009f,4020667866">琪亚娜生日快乐</d>  
  <d p="5.41200,1,25,16777215,1512705139,0,55ed3c6d,4020695901">66666666</d>  
  <d p="39.65400,1,25,16777215,1512705321,0,52510030,4020699904">头皮发麻</d>  
  <d p="180.66900,1,25,16777215,1512705489,0,52510030,4020703726">全程头皮发麻</d>  
  <d p="25.66000,1,25,16777215,1512705422,0,6574e345,4020709978">琪亚娜生日快乐</d>  
  <d p="40.39900,1,25,16777215,1512706275,0,b1156584,4020724468">2333</d>  
  <d p="66.58500,1,25,16777215,1512706301,0,719acbe,4020725150">kiana,happy birthday!</d>  
  <d p="119.24200,1,25,16777215,1512706354,0,719acbe,4020726536">大神就是如此吧</d>  
  <d p="41.73900,1,25,16777215,1512706303,0,c771bdbe,4020728035">kiana生日快乐</d>  
  <d p="59.01100,1,25,16777215,1512706429,0,f4e49e99,4020728636">Kiana生日快乐</d>  
  <d p="189.05800,1,25,16777215,1512706164,0,719acbe,4020729246">不消说，这硬币我给!</d>  
  <d p="114.45600,1,25,16777215,1512706512,0,d1c0de7a,4020731024">kiana happy birthday</d>  
  <d p="54.79600,1,25,16777215,1512707597,0,c88fb301,4020765878">kiana生日快乐</d>  
  <d p="114.55500,1,25,16777215,1512707936,0,78eb905d,4020782443">kiana生日快乐</d>  
  <d p="116.70900,1,25,16777215,1512708494,0,ca1ca72c,4020803457">这次的录音音效有点混？</d>  
  <d p="93.95100,1,25,16777215,1512710094,0,62941bab,4020863804">kiana happy birthday</d>  
  <d p="38.76100,1,25,16777215,1512712293,0,f9b9ce0a,4020929241">琪亚娜生日快乐！！！！！</d>  
  <d p="40.82300,1,25,16777215,1512712337,0,810ffc3e,4020930369">熟悉的施坦威，a叔毕业后又去学院了，还是提前录好的</d>  
  <d p="7.72000,1,25,16777215,1512712681,0,cce5353a,4020938889">来啦来啦</d>  
  <d p="119.26000,1,25,16777215,1512713754,0,93fe52ab,4020966364">第五章最后一个boss二阶段的bgm</d>  
  <d p="49.85900,1,25,16777215,1512714064,0,252b7832,4020971062">琪亚娜生快</d>  
  <d p="65.86100,1,25,16777215,1512714437,0,4a416e69,4020979114">kiana生日快乐</d>  
  <d p="32.59000,1,25,16777215,1512715471,0,69e3ae80,4021003072">好棒啊</d>  
  <d p="68.70000,1,25,16777215,1512715369,0,cdf3b00c,4021007312">kiana生日快乐！</d>  
  <d p="55.82600,1,25,16777215,1512715850,0,1019e61,4021011766">小公主生日快乐</d>  
  <d p="68.94400,1,25,16777215,1512716418,0,e18cf09a,4021025053">琪亚娜生日快乐</d>  
  <d p="218.74900,1,25,16777215,1512716823,0,27291036,4021034319">生日快乐</d>  
  <d p="0.00000,1,25,16777215,1512716838,0,27291036,4021034654">压灭路</d>  
  <d p="81.19400,1,25,16777215,1512717021,0,cdbac730,4021038932">琪亚娜生日快乐</d>  
  <d p="36.63900,1,25,16777215,1512717354,0,6e4a5dc0,4021046437">琪亚娜生日快乐！</d>  
  <d p="40.02900,1,25,16777215,1512717490,0,1ccccabd,4021049567">许愿月光</d>  
  <d p="36.11200,1,25,16777215,1512717766,0,accd1a54,4021056235">kiana生日快乐</d>  
  <d p="97.11600,1,25,16777215,1512718742,0,de77316e,4021079566">kiana生日快乐</d>  
  <d p="6.96400,1,25,16777215,1512719120,0,6a9d7d09,4021088208">硬币已投！！！！！！！！！！</d>  
  <d p="62.61900,1,25,16777215,1512719213,0,6a9d7d09,4021090354">琪亚娜生日快乐！</d>  
  <d p="56.22000,1,25,16777215,1512719242,0,99c074d1,4021093335">女儿生日快乐</d>  
  <d p="182.44900,1,25,16777215,1512719434,0,fb833bc7,4021095376">阿湿波听到这首曲子瑟瑟发抖.......</d>  
  <d p="87.32200,1,25,16777215,1512719735,0,3964181b,4021102528">生日快乐</d>  
  <d p="50.39400,1,25,16777215,1512720853,0,8b93d212,4021128928">！！！</d>  
  <d p="38.22900,1,25,16777215,1512721246,0,4ebdc3f0,4021138641">琪亚娜生日快乐</d>  
  <d p="79.62300,1,25,16777215,1512721349,0,16923789,4021141167">Kiana生日快乐</d>  
  <d p="7.70600,1,25,16777215,1512721449,0,8b93d212,4021144056">惊了！</d>  
  <d p="190.95000,1,25,16777215,1512721710,0,413e47df,4021150096">kana生日快乐⸂⸂⸜(രᴗര๑)⸝⸃⸃</d>  
  <d p="67.30200,1,25,16777215,1512721724,0,3665a313,4021150472">Kiana生日快乐！</d>  
  <d p="86.22200,1,25,16777215,1512722476,0,c57929,4021172874">祝你生日快乐送我月光</d>  
  <d p="36.82100,1,25,16777215,1512722768,0,e7bfbbbf,4021177941">琪亚娜生日快乐</d>  
  <d p="43.25700,1,25,16777215,1512722834,0,d62e044,4021179710">生日快乐 ！！！Kiana大小姐</d>  
  <d p="3.32800,1,25,16777215,1512723378,0,f379d777,4021194590">作为崩2的玩家表示哭泣</d>  
  <d p="222.57700,1,25,16777215,1512723420,0,17dbe4c5,4021195845">好想用来做铃声</d>  
  <d p="62.17200,1,25,16777215,1512724173,0,6da39272,4021218031">琪亚娜生日快乐</d>  
  <d p="14.13900,1,25,16777215,1512724418,0,dcd21da9,4021225289">失踪人口回归</d>  
  <d p="7.42800,1,25,16777215,1512724882,0,f0bebc1f,4021239599">琪亚娜生日快乐</d>  
  <d p="224.72300,5,25,65535,1512724961,0,c6e06645,4021242044">满配誓约二十秒撸阿湿婆不是吹~~</d>  
  <d p="214.72200,1,25,16777215,1512725330,0,5dbcf73f,4021256551">崩坏世界的歌姬！！！</d>  
  <d p="4.98000,1,25,16777215,1512725889,0,21787a5c,4021273855">哦哦哦哦哦哦！</d>  
  <d p="12.70000,1,25,16777215,1512725725,0,21787a5c,4021274415">kiana公主生日快乐！</d>  
  <d p="43.99600,1,25,16777215,1512726570,0,648815b8,4021292936">生快琪亚娜</d>  
  <d p="123.13600,1,25,16777215,1512726702,0,a6b766ef,4021297284">琪亚娜生日快乐</d>  
  <d p="36.80600,1,25,6750207,1512726930,0,80a4e9a8,4021305093">琪亚娜生日快乐</d>  
  <d p="90.13300,1,25,6750207,1512727007,0,80a4e9a8,4021307775">永远的月光公主生日快乐</d>  
  <d p="31.26000,1,25,16777215,1512727161,0,120f8c28,4021313876">lch liebe dich</d>  
  <d p="4.30000,1,25,16777215,1512726910,0,cb0239b2,4021314487">琪安娜生日快乐</d>  
  <d p="7.91100,1,25,16777215,1512727208,0,c96329d5,4021315529">赞赞赞赞</d>  
  <d p="71.15200,1,25,16777215,1512727292,0,c96329d5,4021318639">老婆生日快乐</d>  
  <d p="5.42400,1,25,16777215,1512728617,0,ee8578b6,4021367034">我刷出了什么？</d>  
  <d p="32.26000,1,25,16777215,1512728644,0,ee8578b6,4021368061">琪亚娜生日快乐</d>  
  <d p="57.34300,1,25,16777215,1512729631,0,b41076f4,4021407566">kianna生日快乐！</d>  
  <d p="77.63200,1,25,16777215,1512729665,0,b41076f4,4021409064">kiana生日快乐！</d>  
  <d p="79.89400,1,25,16777215,1512730352,0,5f824661,4021437675">琪安娜生日快乐</d>  
  <d p="28.95800,1,25,16777215,1512730560,0,d25dbf7c,4021446621">琪亚娜生日快乐</d>  
  <d p="35.80800,1,25,16777215,1512730691,0,4ed95e00,4021452200">大佬大佬</d>  
  <d p="183.17900,1,25,16777215,1512730728,0,63dc8d24,4021453783">琪亚娜生日快乐</d>  
  <d p="74.91400,1,25,16777215,1512730696,0,35fda224,4021456780">琪亚娜生日快乐</d>  
  <d p="165.29100,1,25,16777215,1512731244,0,2b6372d8,4021475762">三手技巧？</d>  
  <d p="93.40700,1,25,16777215,1512731505,0,c096927a,4021486970">琪亚娜生日快乐！！！！！！！！！！！！！！！！！</d>  
  <d p="2.21900,1,25,16777215,1512731759,0,1d309c0d,4021497756">chat:youngb-2 高阶服饰 100%原版打版</d>  
  <d p="209.19000,1,25,15138834,1512731761,0,bd8d6057,4021502200">崩坏世界的歌姬！！！</d>  
  <d p="91.26600,1,25,16777215,1512731916,0,2b21c8da,4021508576">我最爱的游戏+我最爱的手</d>  
  <d p="222.64500,1,25,16777215,1512732580,0,541f18dc,4021533196">许愿上岸</d>  
  <d p="111.23400,1,25,10066329,1512732595,0,48bcce90,4021533859">A叔还是一如既往的叼</d>  
  <d p="42.18100,1,25,15138834,1512732647,0,3953c03a,4021540734">kiana生日快乐</d>  
  <d p="18.19100,5,25,16777215,1512733375,0,bb538667,4021568693">这是什么手速？</d>  
  <d p="76.95400,1,25,16777215,1512733385,0,d8835c68,4021569144">kiana生日快乐</d>  
  <d p="202.31700,1,25,16777215,1512733858,0,d00965ee,4021590695">好厉害啊。。。。。</d>  
  <d p="10.56100,1,25,16777215,1512734097,0,f2eb320,4021601614">哇我刷出了什么</d>  
  <d p="43.60000,1,25,16707842,1512734434,0,a215029c,4021617326">草履虫生日快乐</d>  
  <d p="76.18200,1,25,16777215,1512734571,0,90380e9c,4021628997">kiana 生日快乐</d>  
  <d p="2.16300,1,25,16777215,1512734735,0,a01016e1,4021631899">猝不及防的更新</d>  
  <d p="46.97700,1,25,16777215,1512734798,0,98121904,4021634836">大小姐生快????</d>  
  <d p="32.84200,1,25,16777215,1512734589,0,a4b96c5e,4021638583">琪亚娜生日快乐</d>  
  <d p="43.11900,1,25,16777215,1512734974,0,7ec2540e,4021648177">Kiana生日快乐！</d>  
  <d p="90.89900,1,25,16777215,1512736020,0,311d063c,4021706044">Kiana生日快乐</d>  
  <d p="72.82800,1,25,16777215,1512736357,0,3dda26cc,4021708359">111111111111</d>  
  <d p="94.34800,1,25,15138834,1512736417,0,c7332b94,4021711222">火钳刘明</d>  
  <d p="163.77700,1,25,15138834,1512736491,0,c7332b94,4021715525">←卡农的我给你刷一波666666</d>  
  <d p="76.36000,1,25,16777215,1512736549,0,5de372fa,4021717444">good,i like it</d>  
  <d p="20.65700,1,25,16777215,1512736769,0,d58c91ca,4021727934">！！！！！！！！！！</d>  
  <d p="16.68400,1,25,16777215,1512736921,0,fd0ce8a7,4021735129">琪亚娜生日快乐！</d>  
  <d p="127.90700,1,25,16777215,1512736655,0,195232c6,4021736049">名字带林的女歌手总喜欢这种调调。。。</d>  
  <d p="133.62200,1,25,16777215,1512737013,0,ec550bc1,4021744381">呐，白毛丫头，生日快乐(◦`~´◦)</d>  
  <d p="39.61600,1,25,16777215,1512737583,0,c266542b,4021765930">琪亚纳生日快乐</d>  
  <d p="52.80000,1,25,16777215,1512737604,0,ef190f16,4021766919">shengjuai</d>  
  <d p="55.10000,1,25,16777215,1512737612,0,ef190f16,4021767315">生快</d>  
  <d p="68.77900,1,25,16777215,1512737663,0,3c7d6a12,4021769833">kiana生日快乐</d>  
  <d p="94.67500,1,25,16777215,1512737713,0,3c7d6a12,4021772147">永远的月光公主kiana</d>  
  <d p="208.97800,1,25,16777215,1512737432,0,86601f48,4021772396">瞬间一身鸡皮疙瘩</d>  
  <d p="12.91200,1,25,15138834,1512737755,0,c7332b94,4021774074">为什么有一种星球大战片头曲的感觉………………</d>  
  <d p="101.67600,1,25,16777215,1512738052,0,f6c1cbe4,4021789141">最爱的游戏+最爱的手+1</d>  
  <d p="166.39000,1,25,16777215,1512738151,0,f6c1cbe4,4021792866">卡农的厉害了</d>  
  <d p="179.81900,1,25,8700107,1512738178,0,dd9c2498,4021794907">偷偷抱走八重樱</d>  
  <d p="43.96000,1,25,16777215,1512738582,0,d9d2c584,4021813088">许愿勿忘。月光</d>  
  <d p="32.18400,1,25,16777215,1512738944,0,805d582d,4021830874">琪亚娜生日快乐</d>  
  <d p="87.59900,1,25,16777215,1512738998,0,fd7af373,4021833613">kiana生日快乐</d>  
  <d p="216.29200,1,25,16777215,1512739180,0,fd7af373,4021842600">歌姬</d>  
  <d p="30.05600,1,25,16777215,1512739439,0,22cf4229,4021855495">琪亚娜生日快乐</d>  
  <d p="70.74300,1,25,16777215,1512739514,0,9aaaa090,4021859168">琪安娜生日快乐</d>  
  <d p="102.52600,1,25,16777215,1512739618,0,22cf4229,4021864146">琪亚娜生日快乐！</d>  
  <d p="69.92000,1,25,16777215,1512740308,0,2b7a806d,4021898311">琪亚娜生日快乐</d>  
  <d p="110.64000,1,25,16777215,1512740498,0,1d393f39,4021907861">琪亚娜生日快乐！</d>  
  <d p="133.97700,1,25,16777215,1512740693,0,65f90666,4021917826">悄悄许愿月光！</d>  
  <d p="94.83400,1,25,16777215,1512740503,0,aca8cae2,4021922729">卧槽，大神啊。这手速惊了</d>  
  <d p="27.78400,1,25,16777215,1512741418,0,b99dd2ba,4021966237">生活圈又一次交叉了</d>  
  <d p="89.93100,1,25,16777215,1512741792,0,e5347c6d,4021986330">琪亚娜~生日快乐~</d>  
  <d p="71.57200,1,25,16777215,1512741864,0,4dcb4a2a,4021990272">kiana生日快乐</d>  
  <d p="115.82000,1,25,16777215,1512741915,0,533d5b5e,4021993136">所以玩崩3必须要这种手速吗。。</d>  
  <d p="44.29400,1,25,16777215,1512741922,0,a113eec9,4021994515">琪亚娜生日快乐</d>  
  <d p="116.94700,1,25,16777215,1512742167,0,b301614e,4022006738">琪亚娜生日快乐</d>  
  <d p="44.82400,1,25,16777215,1512742878,0,3f02d157,4022045298">琪亚娜小公举生日快乐！！！</d>  
  <d p="24.04000,1,25,16777215,1512743423,0,20e6e764,4022074756">缇娅娜生日快乐</d>  
  <d p="68.21200,1,25,16777215,1512743439,0,1467671a,4022075637">生日快乐</d>  
  <d p="161.01000,1,25,16777215,1512743566,0,b08c58b6,4022082458">kiana，生日快乐</d>  
  <d p="45.70500,1,25,16777215,1512743673,0,afb8f498,4022088190">琪亚娜生日快乐</d>  
  <d p="51.85100,1,25,16777215,1512743751,0,cc225128,4022092256">琪亚娜生日快乐</d>  
  <d p="64.44800,1,25,16777215,1512743944,0,38b5836,4022102711">琪亚娜生日快乐！</d>  
  <d p="90.40400,1,25,16777215,1512744807,0,bc27b684,4022148683">kiana生日快乐</d>  
  <d p="119.06000,4,25,41194,1512744528,0,a4cb12eb,4022149064">琪亚娜生日快乐！</d>  
  <d p="72.40000,1,25,16777215,1512744753,0,9b2be6b7,4022151397">琪亚娜生日快乐ｸﾞｯ!(๑•̀ㅂ•́)و✧</d>  
  <d p="142.24900,4,25,41194,1512744869,0,a4cb12eb,4022151932">高级弹幕</d>  
  <d p="131.99800,1,25,16777215,1512745509,0,e7fc3bb3,4022185248">听着听着为什么总想哭(┯_┯)</d>  
  <d p="64.28100,1,25,16777215,1512745540,0,2cde88cc,4022186937">大伟哥给钱了？？？</d>  
  <d p="108.49900,1,25,16777215,1512745857,0,bf81dcc1,4022203659">害得我去刷火傻碎片了</d>  
  <d p="91.99000,1,25,16777215,1512746660,0,c491001e,4022245457">八重樱的那个站住，你休想！！！</d>  
  <d p="108.31700,1,25,16777215,1512746833,0,184c87b1,4022254377">琪亚娜生日快乐！</d>  
  <d p="31.86100,1,25,16777215,1512746936,0,60625323,4022259679">许愿月光</d>  
  <d p="215.18600,1,25,16777215,1512746993,0,2c1a708d,4022262626">Kiana生日快乐</d>  
  <d p="27.98900,1,25,16777215,1512747867,0,87e28bb9,4022307206">琪亚娜你是公主啊！</d>  
  <d p="42.53300,1,25,16777215,1512748052,0,8975e595,4022316371">kiana生日快乐</d>  
  <d p="13.80100,1,25,16777215,1512748140,0,6dc34b15,4022320580">kiana小公主生日快乐</d>  
  <d p="123.36900,1,25,16777215,1512748309,0,93b57f1c,4022328871">琪亚娜生日快乐！！</d>  
  <d p="132.40300,1,25,16777215,1512748319,0,93b57f1c,4022329313">琪亚娜生日快乐！！</d>  
  <d p="135.65500,5,25,11890,1512748061,0,93b57f1c,4022330729">琪亚娜生日快乐！</d>  
  <d p="43.99200,1,25,16777215,1512748849,0,492432c8,4022358510">Happy</d>  
  <d p="45.51200,5,25,15138834,1512748998,0,492432c8,4022360433">HAPPY BIRTHDAY TO MY LOVE KIANA</d>  
  <d p="110.95900,1,25,16777215,1512750226,0,414c564e,4022411804">觉得这里开始超好听的只有我一个吗！？</d>  
  <d p="143.20600,1,25,16777215,1512750181,0,414c564e,4022413473">这里开始特别燃！！</d>  
  <d p="144.74300,1,25,16777215,1512750297,0,414c564e,4022413853">重要的fa说三次n</d>  
  <d p="160.27800,1,25,16777215,1512750328,0,414c564e,4022415046">安静滴沉醉在音乐的海洋里吧！！！</d>  
  <d p="8.20500,1,25,16777215,1512751084,0,efcfd670,4022443404">kiana生日快乐！！！</d>  
  <d p="198.48100,1,25,16777215,1512752173,0,3778f3e5,4022480047">第五章boss打的我头疼</d>  
  <d p="51.49900,1,25,16777215,1512752913,0,81e89fcc,4022502701">小公主生日快乐</d>  
  <d p="149.42200,1,25,16777215,1512759089,0,4621e292,4022615805">为什么音画不同步？？</d>  
  <d p="55.48600,1,25,16777215,1512759421,0,202ef19a,4022619700">琪亚娜生日快乐</d>  
  <d p="41.40000,1,25,16777215,1512773550,0,28107dd3,4022702308">kiana生日快乐</d>  
  <d p="112.75000,1,25,16777215,1512776596,0,2dadded7,4022727926">happy birthday to Kiana</d>  
  <d p="79.57800,1,25,16777215,1512777206,0,659ccadc,4022738806">琪亚娜生日快乐</d>  
  <d p="66.61000,1,25,16777215,1512778612,0,b3b6f02c,4022754371">白毛团子，生日快乐。</d>  
  <d p="17.74000,1,25,16777215,1512779151,0,711735d1,4022763023">琪亚娜生日快乐，月光来我怀里</d>  
  <d p="86.00000,1,25,16777215,1512779185,0,e77e783,4022763611">许愿月光！！！！</d>  
  <d p="12.73000,1,25,16777215,1512779781,0,4e006aa4,4022773752">666666</d>  
  <d p="38.34300,1,25,16777215,1512779806,0,4e006aa4,4022774192">手速可以的</d>  
  <d p="42.92300,1,25,16777215,1512780099,0,1501b804,4022779813">琪亚娜生日快乐</d>  
  <d p="93.88900,1,25,16777215,1512780416,0,4de50842,4022796729">生日快乐kiyana</d>  
  <d p="78.00500,1,25,16777215,1512782443,0,f74a83a0,4022841910">Kiana生快</d>  
  <d p="199.93400,1,25,16777215,1512782897,0,988c8c75,4022853871">然而进度条告诉我没那么简单</d>  
  <d p="83.97400,1,25,16777215,1512784277,0,3f17f224,4022890945">琪亚娜生日快乐</d>  
  <d p="125.60100,1,25,16777215,1512784583,0,30363e6,4022899448">斯坦威的音色好美，中间那两下炸耳朵的好听</d>  
  <d p="142.95000,1,25,16711680,1512785355,0,5991a870,4022921960">琪亚娜生日快乐</d>  
  <d p="66.53900,1,25,16777215,1512786055,0,207724b3,4022946318">6666</d>  
  <d p="30.96700,1,25,16777215,1512786268,0,befada54,4022949623">海上钢琴师</d>  
  <d p="61.12100,1,25,16777215,1512786342,0,59512c6a,4022951915">许愿月光</d>  
  <d p="18.72200,1,25,16777215,1512787528,0,d486a5d4,4022990353">琪亚娜生日快乐</d>  
  <d p="130.29700,1,25,16777215,1512788719,0,1c30feb5,4023031881">A叔太厉害了！琪亚娜生日快乐</d>  
  <d p="224.48700,1,25,16777215,1512788851,0,1c30feb5,4023036362">逝去个毛，崩崩还能再战五百年！</d>  
  <d p="11.19900,1,25,16777215,1512789137,0,414c564e,4023049974">说广告的那位你哪来的权利替a叔发言？请尊重艺术家！</d>  
  <d p="54.14000,1,25,16777215,1512789418,0,4205b6aa,4023065586">琪安娜生日快乐！</d>  
  <d p="38.40000,1,25,16777215,1512791088,0,80046529,4023114151">琪亚娜生日快乐</d>  
  <d p="57.83700,1,25,16777215,1512791232,0,a07ee78f,4023119371">许愿月光</d>  
  <d p="49.60100,1,25,16777215,1512793134,0,86586459,4023196874">Ich Liebe Dich</d>  
  <d p="50.12200,1,25,16777215,1512794073,0,e8382a40,4023232910">琪亚娜 生日快乐 虽然我已经弃坑了 祝你在新的舰长那里一切安好</d>  
  <d p="138.48100,1,25,16777215,1512794365,0,acffef11,4023246237">蔡依林？</d>  
  <d p="84.56500,1,25,16777215,1512794612,0,3e7b53d4,4023257414">Kiana生日快乐</d>  
  <d p="57.81700,5,25,26367,1512794636,0,bbb4f1ff,4023258485">琪亚娜生日快乐</d>  
  <d p="21.07200,5,25,15772458,1512795175,0,bb53c41e,4023289083">琪亚娜生日快乐</d>  
  <d p="44.75900,1,25,16777215,1512795771,0,40b7c547,4023311750">生快琪亚娜</d>  
  <d p="70.26300,1,25,16777215,1512796503,0,29161418,4023346486">kiana生日快乐</d>  
  <d p="70.47600,1,25,16777215,1512796567,0,292c2f72,4023348634">kiana生日快乐</d>  
  <d p="230.36000,1,25,16777215,1512797564,0,40b7c547,4023393654">崩二啊</d>  
  <d p="91.73300,1,25,16777215,1512797690,0,240b3cef,4023399422">琪亚娜生日快乐</d>  
  <d p="97.73100,1,25,16777215,1512797833,0,7542bff6,4023410415">kiana生日快乐！！！</d>  
  <d p="1.36500,1,25,16777215,1512797988,0,f0f53ff3,4023412612">你是我最怕的boss</d>  
  <d p="66.36800,1,25,16777215,1512798198,0,965799bd,4023421909">琪亚娜生日快乐</d>  
  <d p="140.65100,1,25,16777215,1512798266,0,2b4f85ca,4023424979">痞老板生日快乐</d>  
  <d p="33.66500,5,25,16711680,1512798857,0,d238bcda,4023450653">琪亚娜生日快乐</d>  
  <d p="67.74900,1,25,16777215,1512798884,0,aaf1f0e7,4023451845">琪亚娜生快www</d>  
  <d p="216.24500,1,25,16777215,1512799034,0,aaf1f0e7,4023458111">崩崩！</d>  
  <d p="12.18500,1,25,16777215,1512799562,0,95dfbf34,4023479807">kiana小公主生日快乐</d>  
  <d p="143.57800,1,25,16777215,1512799617,0,19cd8a24,4023481962">为这个美好的世界献上硬币</d>  
  <d p="34.98000,1,25,16777215,1512800578,0,165ed79,4023520551">喜欢了很多年了</d>  
  <d p="41.09700,1,25,16777215,1512802258,0,4309fad7,4023585784">琪亚娜生日快乐！！</d>  
  <d p="222.64900,1,25,16777215,1512803232,0,61a7ca3b,4023623475">崩坏世界的歌姬</d>  
  <d p="82.77900,1,25,16777215,1512804558,0,78026a4e,4023674130">琪亚娜生日快乐！</d>  
  <d p="59.44000,1,25,16777215,1512806016,0,af7ebde3,4023731198">琪亚娜生日快乐</d>  
  <d p="49.12500,1,25,16777215,1512806052,0,cccdee,4023732653">琪亚娜生日快乐</d>  
  <d p="92.34100,1,25,16777215,1512806059,0,af7ebde3,4023732914">我看见了，少年</d>  
  <d p="86.54200,1,25,0,1512806090,0,cccdee,4023734077">琪亚娜生日快乐</d>  
  <d p="112.59500,1,25,16777215,1512806628,0,e74a5784,4023755669">琪亚娜生日快乐</d>  
  <d p="122.78300,1,25,16777215,1512807474,0,ff0cb8ef,4023789361">琪亚娜生日快乐</d>  
  <d p="23.74000,5,25,16777215,1512808394,0,1152ef72,4023826791">难道这是a叔自己的琴吗？</d>  
  <d p="57.37600,1,25,16777215,1512809103,0,c63933b9,4023855625">a叔手痩了的带我一个</d>  
  <d p="101.63500,1,25,16777215,1512809384,0,59c0466d,4023867157">琪亚娜生日快乐！</d>  
  <d p="201.42000,1,25,16777215,1512810161,0,4be0959,4023899239">的确音画不同步</d>  
  <d p="43.74200,1,25,16777215,1512812493,0,e99885c8,4023997703">许愿月光</d>  
  <d p="87.11500,1,25,16777215,1512813097,0,4a927aad,4024024034">琪亚娜生日快乐</d>  
  <d p="64.94000,1,25,16777215,1512814887,0,e717e26b,4024103863">怎么可以这么美，为A叔打call!</d>  
  <d p="197.97900,1,25,16777215,1512816158,0,f4fd0071,4024164510">前方高能</d>  
  <d p="42.73300,1,25,16777215,1512817906,0,84147345,4024251572">kiana生日快乐！！！</d>  
  <d p="76.46700,1,25,16777215,1512817941,0,84147345,4024253182">许愿两个傻德</d>  
  <d p="177.81500,1,25,16777215,1512817953,0,7d6417fc,4024253864">草履虫生日快乐！！！！</d>  
  <d p="199.56600,1,25,52224,1512817975,0,7d6417fc,4024254991">承包草履虫</d>  
  <d p="42.23500,1,25,16777215,1512818037,0,e042cd82,4024258115">好听</d>  
  <d p="25.89300,1,25,16777215,1512818131,0,aeeceda7,4024262855">kiana生日快乐</d>  
  <d p="130.53100,1,25,16777215,1512818150,0,30757964,4024263886">许愿月光啊！！！~~</d>  
  <d p="42.42100,1,25,16777215,1512819317,0,c56d659,4024324567">琪亚娜生日快乐</d>  
  <d p="94.68000,1,25,16777215,1512820252,0,123d5517,4024373768">生日快乐</d>  
  <d p="84.96500,1,25,16777215,1512820942,0,a9eda319,4024409327">许愿月光</d>  
  <d p="107.51900,1,25,16777215,1512821931,0,626bf936,4024461369">看的小指发疼</d>  
  <d p="200.78900,1,25,15138834,1512822147,0,a86ed056,4024472837">好听</d>  
  <d p="7.61300,1,25,16777215,1512822345,0,5fba5973,4024483182">6666666</d>  
  <d p="4.67800,1,25,16777215,1512822388,0,417c48c2,4024486487">莫名觉得开头像二小姐</d>  
  <d p="24.92200,1,25,16777215,1512822462,0,9c07300,4024489504">随意许愿深红</d>  
  <d p="145.29400,1,25,16777215,1512823142,0,e3225a16,4024525461">许愿电磁炮</d>  
  <d p="17.54000,1,25,16777215,1512823243,0,67f9dc89,4024536208">啊啊啊，头一次这么前。</d>  
  <d p="60.80000,1,25,16777215,1512824161,0,7cf2a45e,4024580110">Kiana生日快乐</d>  
  <d p="115.50300,1,25,16777215,1512824331,0,88c5a2cc,4024588797">666</d>  
  <d p="210.63800,1,25,16777215,1512824389,0,7cf2a45e,4024590889">崩坏世界的歌姬！！！</d>  
  <d p="0.64700,1,25,16777215,1512824780,0,40b3e06d,4024610742">草履虫生日快乐！！！！！</d>  
  <d p="52.60800,1,25,41194,1512825301,0,aa1da53d,4024637791">鱼，好大的鱼.....对不起我走错了</d>  
  <d p="101.90600,1,25,16777215,1512826712,0,c46442cc,4024711171">琪亚娜生日快乐</d>  
  <d p="40.98600,1,25,16777215,1512827584,0,e1f3b490,4024758971">这个很简单的，八级左右的曲子</d>  
  <d p="36.72100,1,25,16777215,1512827759,0,e094f66,4024768011">我也就每天10</d>  
  <d p="161.10000,1,25,16777215,1512827803,0,d9452041,4024770623">迟到的的祝福，琪亚娜生日快乐</d>  
  <d p="99.89300,1,25,16777215,1512827980,0,7760cc89,4024780509">我的小公主，生日快乐</d>  
  <d p="32.53900,1,25,16777215,1512828729,0,90596fef,4024831762">米哈游动画公司？</d>  
  <d p="132.22900,1,25,16777215,1512828829,0,90596fef,4024838271">没有sss月光，居然还敢说爱她</d>  
  <d p="127.04200,1,25,16777215,1512828829,0,bb7cdb97,4024838288">A叔</d>  
  <d p="177.30400,1,25,16777215,1512829550,0,7a5806e3,4024885944">预测一波，姨妈生日必弹星与你的消失之日~</d>  
  <d p="56.45100,1,25,16777215,1512829880,0,62098af1,4024913686">琪亚娜生日快乐</d>  
  <d p="89.19700,1,25,16777215,1512830256,0,401f4d6d,4024930369">公主生日快乐!(^O^)y</d>  
  <d p="69.10100,1,25,16711680,1512832505,0,fde63a1a,4025059930">琪亚娜生日快乐！！！！</d>  
  <d p="49.88700,1,25,16777215,1512832649,0,8529a0e,4025068172">琪亚娜生日快乐</d>  
  <d p="40.02100,1,25,16777215,1512832511,0,bbafbc47,4025076392">kiana生日快乐♪٩(´ω`)و♪</d>  
  <d p="96.61000,1,25,16777215,1512833077,0,ec11b57d,4025091902">Kiana生日快乐！！！！！！！</d>  
  <d p="171.22200,1,25,16777215,1512833420,0,bbd1381b,4025110451">琪亚娜生日快乐</d>  
  <d p="72.11700,1,25,16777215,1512833588,0,daed0d58,4025119671">前1000！</d>  
  <d p="8.40800,1,25,16777215,1512833701,0,7426c22d,4025125731">666666</d>  
  <d p="211.06000,1,25,16777215,1512835129,0,7afb4263,4025199161">听哭</d>  
  <d p="37.75800,1,25,16777215,1512835777,0,392716bf,4025228929">差不多听到这里阿si波就凉了</d>  
  <d p="214.70000,1,25,16777215,1512836317,0,2a33ea23,4025252627">崩坏世界的歌姬</d>  
  <d p="82.34400,1,25,16777215,1512836436,0,d544bf1,4025257745">许愿次元</d>  
  <d p="107.46400,1,25,16777215,1512836561,0,19ea31b2,4025263115">Kiyana 生日快乐！</d>  
  <d p="50.30400,1,25,16777215,1512836592,0,1ff5fb2a,4025264453">kiana生日快乐！</d>  
  <d p="43.28500,1,25,16777215,1512847740,0,b7954b2b,4025557244">kiana生日快乐</d>  
  <d p="67.41300,1,25,16777215,1512848027,0,62485a55,4025559155">kiana生日快乐</d>  
  <d p="45.29800,5,25,16711680,1512852723,0,4dcb168b,4025595214">这段很像迈克尔杰克逊的earth song 啊</d>  
  <d p="34.73100,1,25,16777215,1512865497,0,4eae2858,4025699361">好听！</d>  
  <d p="193.68400,1,25,16777215,1512865611,0,7e7340b0,4025699498">前方高能</d>  
  <d p="76.74100,1,25,16777215,1512871922,0,6157ac5,4025877738">这玩意不看谱还是挺有难度的</d>  
  <d p="6.56700,1,25,16777215,1512872208,0,fc6e2ead,4025889328">琪亚娜生日快乐</d>  
  <d p="57.30700,1,25,16777215,1512872248,0,87b45dd4,4025890980">kiana生日快乐！</d>  
  <d p="166.44000,1,25,16777215,1512872624,0,3ac26df2,4025906220">给力</d>  
  <d p="102.79900,1,25,16777215,1512872703,0,47729cde,4025909326">A叔就是有能力把我不喜欢的变成喜欢的</d>  
  <d p="57.02400,1,25,16777215,1512873235,0,5cbd0683,4025931152">琪亚娜酱生日快乐~~~！</d>  
  <d p="84.28500,1,25,16777215,1512873455,0,d5c98be4,4025940241">琪亚娜生日快乐啊</d>  
  <d p="29.09500,1,25,16777215,1512874129,0,b089119e,4025968673">失踪人口回归</d>  
  <d p="49.70000,1,25,16711680,1512874150,0,b089119e,4025969541">琪亚娜生日快乐！！！</d>  
  <d p="41.97500,1,25,16777215,1512874252,0,8dedb696,4025974036">看到手上都是残影</d>  
  <d p="62.62600,1,25,16777215,1512875307,0,cf75ae89,4026021379">66666666666</d>  
  <d p="73.76700,1,25,16777215,1512875318,0,cf75ae89,4026021873">666666666</d>  
  <d p="43.01000,1,25,16777215,1512875497,0,4f1c9108,4026029806">kiana生日快乐！</d>  
  <d p="116.49500,1,25,16777215,1512875680,0,4f1c9108,4026037932">救妈神曲</d>  
  <d p="117.75800,1,25,16777215,1512875704,0,95c1200a,4026038941">傻娜生日快乐</d>  
  <d p="210.81400,1,25,16777215,1512875784,0,4f1c9108,4026042370">这是另外一首歌了</d>  
  <d p="36.81100,1,25,16777215,1512876383,0,f2630da7,4026068862">律化娜生日快乐</d>  
  <d p="2.36900,1,25,16777215,1512876638,0,29cf480b,4026080173">琪安娜生日快乐</d>  
  <d p="20.63400,1,25,16777215,1512877799,0,9508e64d,4026134585">Σ(⊙▽⊙"a</d>  
  <d p="72.30100,1,25,16777215,1512877867,0,42f1ea49,4026137606">生日快乐，琪亚娜！Ich！liebe ！dich1</d>  
  <d p="25.13000,1,25,16777215,1512878352,0,fb2c7d3d,4026165508">好听</d>  
  <d p="47.22900,1,25,16777215,1512879340,0,576f350f,4026208313">失踪人口回归</d>  
  <d p="105.51900,1,25,16777215,1512879878,0,d05a607,4026237200">生日快乐</d>  
  <d p="131.37800,1,25,16777215,1512879903,0,d05a607,4026238480">琪娜亚生日快乐</d>  
  <d p="169.14500,1,25,16777215,1512880880,0,2a26068c,4026288365">Kiana生日快乐</d>  
  <d p="102.01900,1,25,16777215,1512882186,0,762aa32c,4026357890">kiana生日快乐！！！</d>  
  <d p="204.34800,1,25,16777215,1512882288,0,762aa32c,4026363403">牛比</d>  
  <d p="34.74700,1,25,16777215,1512882907,0,ed40ed99,4026395857">好听</d>  
  <d p="42.04700,1,25,16777215,1512882932,0,ed40ed99,4026397155">好听</d>  
  <d p="0.08300,1,25,16777215,1512883512,0,b452acdf,4026427321">崩三影响力很大啊！</d>  
  <d p="86.19300,1,25,16777215,1512884906,0,f33aa1db,4026499949">86个一起看的兄弟们好啊 我这是第10遍了</d>  
  <d p="202.33600,1,25,16777215,1512885827,0,3ca67f19,4026546379">崩坏世界的歌姬?!</d>  
  <d p="55.13900,1,25,16777215,1512892271,0,3902d4a0,4026844714">琪亚娜生日快乐，顺带许愿月光！！！！！</d>  
  <d p="136.22000,1,25,16777215,1512895205,0,4c22f86a,4026984254">琪亚娜生日快乐！</d>  
  <d p="10.00100,1,25,16777215,1512898230,0,f4fd0071,4027103653">欢迎回来</d>  
  <d p="145.08200,1,25,16777215,1512899787,0,4be0959,4027169381">崩坏整个结构就和这歌一样庄严的啊，只不过游戏里大多好玩的</d>  
  <d p="89.59000,1,25,16777215,1512901572,0,278e1c22,4027245745">kiana生日快乐</d>  
  <d p="3.12600,1,25,16777215,1512905041,0,8d456da7,4027413990">震震惊</d>  
  <d p="101.83900,1,25,16777215,1512908795,0,276ba4c4,4027569524">我刚刚是不是看到一个说这曲子八级的</d>  
  <d p="73.20200,1,25,16777215,1512910123,0,52feadee,4027629901">琪亚娜生日快乐</d>  
  <d p="34.20300,5,25,16711680,1512911232,0,279ec15,4027680531">kiana生日快乐</d>  
  <d p="110.49800,1,25,16777215,1512911536,0,c90704f2,4027694689">傻娜生日快乐</d>  
  <d p="222.07900,1,25,16777215,1512911646,0,c90704f2,4027699786">崩坏世界的歌姬</d>  
  <d p="95.82900,1,25,16777215,1512913285,0,221a5c9e,4027776951">去你的 八重樱我的</d>  
  <d p="99.66900,1,18,41194,1512913314,0,221a5c9e,4027778376">生日快乐</d>  
  <d p="55.06700,1,25,16777215,1512921028,0,2c634210,4028184378">天天玩崩3我咋不知道有这首歌？？！</d>  
  <d p="47.87200,5,25,16777215,1512924240,0,10f00645,4028297644">许愿次元！！</d>  
  <d p="59.58400,5,18,11890,1512924380,0,10f00645,4028298586">许愿次元</d>  
  <d p="48.57200,1,25,16777215,1512925106,0,90e0eec7,4028325626">kiana生日快乐????</d>  
  <d p="19.65800,1,25,16777215,1512947094,0,4be0959,4028539068">有哪位大佬可以去做个MV肯定好看</d>  
  <d p="83.27500,1,25,16777215,1512967705,0,c7332b94,4028900910">妹妹生日快乐</d>  
  <d p="77.72200,1,25,16777215,1512980233,0,28622592,4029203011">kiana生日快乐，所以给我月光吧</d>  
  <d p="32.91500,1,25,15138834,1512982844,0,c7332b94,4029262525">这首A叔很正常的手速了…………………………</d>  
  <d p="154.15700,1,25,16777215,1512989487,0,61a86694,4029473216">手速害怕</d>  
  <d p="123.02700,1,25,15138834,1512989547,0,c7332b94,4029475496">就技巧而言确实就只有八级啊</d>  
  <d p="146.36400,1,25,15138834,1512989627,0,c7332b94,4029478459">而且两只手也就只有一个主旋律</d>  
  <d p="152.51700,1,25,15138834,1512989560,0,c7332b94,4029479911">你未必要把这首曲子升级为十级或者演奏级?</d>  
  <d p="182.17900,1,25,15138834,1512989716,0,c7332b94,4029481774">这首曲子的技巧而言还没花之舞的技巧要求高</d>  
  <d p="7.50300,1,25,16777215,1513001484,0,859798b1,4029984025">失踪人口回归了？</d>  
  <d p="6.30000,5,25,16707842,1513005676,0,c491001e,4030161669">抽到月光特来还愿</d>  
  <d p="127.02600,1,25,16777215,1513005920,0,e84b7961,4030176711">琪亚娜 生日快乐</d>  
  <d p="5.60500,1,25,16777215,1513047615,0,d1a6729a,4030698477">AAAAA</d>  
  <d p="20.16100,1,25,16777215,1513047628,0,d1a6729a,4030698722">壮我崩三！！！</d>  
  <d p="31.23200,1,25,16777215,1513047653,0,d1a6729a,4030699119">琪亚娜生日快乐！！！！ 我要手炮！！！！</d>  
  <d p="59.77300,1,25,16777215,1513047881,0,d1a6729a,4030702971">突然泪崩</d>  
  <d p="31.71800,1,25,16777215,1513048260,0,d1a6729a,4030709329">I'm swallowed whole</d>  
  <d p="31.71800,4,25,13369344,1513048283,0,d1a6729a,4030709707">I'm swallowed whole</d>  
  <d p="31.71800,4,25,13369344,1513048291,0,d1a6729a,4030709847">我轻易的</d>  
  <d p="34.86300,4,25,13369344,1513048319,0,d1a6729a,4030710384">inside this chaotic world so easily</d>  
  <d p="38.05900,4,25,16724736,1513048730,0,d1a6729a,4030717148">被这崩坏世界所吞噬</d>  
  <d p="42.27500,4,25,16724736,1513048754,0,d1a6729a,4030717522">Silent wind just blows across an</d>  
  <d p="42.27500,4,25,16724736,1513048761,0,d1a6729a,4030717638">静默的风</d>  
  <d p="46.51400,4,25,16724736,1513048934,0,d1a6729a,4030720667">interspace between light and dark.</d>  
  <d p="46.51400,4,25,16724736,1513048943,0,d1a6729a,4030720783">在光明与黑暗中掠过</d>  
  <d p="52.77000,4,25,16724736,1513049057,0,d1a6729a,4030722728">I was born out of this great divide,</d>  
  <d p="52.77000,4,25,16724736,1513049065,0,d1a6729a,4030722856">我于边界诞生</d>  
  <d p="58.74200,4,25,16724736,1513049096,0,d1a6729a,4030723529">runs through the barren ground.</d>  
  <d p="58.74200,4,25,16724736,1513049103,0,d1a6729a,4030723655">踏过每一寸贫瘠之地</d>  
  <d p="58.74200,4,25,16724736,1513049161,0,d1a6729a,4030724681">（为了我大崩三而写字幕 (´・ω・)ﾉ）</d>  
  <d p="62.24400,4,25,16724736,1513050429,0,d1a6729a,4030746982">I need to live my life enough</d>  
  <d p="62.24400,4,25,16724736,1513050438,0,d1a6729a,4030747141">我必竭尽全力</d>  
  <d p="65.85200,4,25,16724736,1513050493,0,d1a6729a,4030748159">before all the leaves fall to pieces</d>  
  <d p="65.85200,4,25,16724736,1513050500,0,d1a6729a,4030748297">直到所有美好都已消逝</d>  
  <d p="69.48700,4,25,16724736,1513050536,0,d1a6729a,4030748944">till I am burned out.</d>  
  <d p="69.48700,4,25,16724736,1513050543,0,d1a6729a,4030749075">绽放我的生命</d>  
  <d p="72.06700,4,25,16724736,1513050572,0,d1a6729a,4030749608">Oh, my body knows...</d>  
  <d p="72.06700,4,25,16724736,1513050586,0,d1a6729a,4030749866">噢！身躯已经唤醒</d>  
  <d p="72.06700,4,25,16724736,1513050797,0,d1a6729a,4030753883">（让我休息一会。。。）</d>  
  <d p="75.15100,4,25,16724736,1513051263,0,d1a6729a,4030762924">Just like my blood,</d>  
  <d p="75.15100,4,25,16724736,1513051273,0,d1a6729a,4030763106">如同血液已然沸腾！</d>  
  <d p="73.13100,1,25,16777215,1513052140,0,b0f6f951,4030782798">鱼 好大的鱼 虎纹鲨鱼</d>  
  <d p="78.07200,4,25,16724736,1513052635,0,d1a6729a,4030796272">our fight still keeps flowing</d>  
  <d p="78.07200,4,25,16724736,1513052642,0,d1a6729a,4030796473">战斗永不停息</d>  
  <d p="81.49000,4,25,16724736,1513052749,0,d1a6729a,4030799521">下面的挡队形啦。。。（还是一样的红-_-）</d>  
  <d p="81.99600,1,25,16777215,1513052901,0,d1a6729a,4030804010">I must struggle to survive</d>  
  <d p="81.99600,1,25,16777215,1513052912,0,d1a6729a,4030804358">我必须生存下去</d>  
  <d p="81.26700,1,25,16777215,1513053029,0,d1a6729a,4030807988">我必须生存下去I must struggle to survive</d>  
  <d p="83.86100,4,25,16724736,1513053051,0,d1a6729a,4030808703">I must struggle to survive</d>  
  <d p="83.86100,4,25,16724736,1513053058,0,d1a6729a,4030808915">我必须生存下去</d>  
  <d p="89.37000,4,25,16724736,1513053137,0,d1a6729a,4030811317">我不行了。。。。</d>  
  <d p="89.37000,4,25,16724736,1513053154,0,d1a6729a,4030811892">有人能接下我吗？</d>  
  <d p="185.27800,1,25,16777215,1513062736,0,8b93d212,4031054405">技巧没有花之舞难？你在逗我？</d>  
  <d p="7.80700,1,25,16777215,1513063236,0,5190d1c4,4031063885">？？？</d>  
  <d p="189.28400,1,25,16777215,1513075936,0,75113f4b,4031375562">好听</d>  
  <d p="207.42900,1,25,16777215,1513075954,0,75113f4b,4031376240">哈哈好听</d>  
  <d p="27.95400,1,25,16777215,1513079531,0,fbfe3e8c,4031506664">我靠重影</d>  
  <d p="18.20300,1,25,16777215,1513082422,0,e1bd96bb,4031613370">琪亚娜生日快乐</d>  
  <d p="92.22100,1,25,16777215,1513084401,0,1d42e6a9,4031701233">感谢红字大佬</d>  
  <d p="0.80000,5,25,15138834,1513088175,0,eab1d4b5,4031852704">此曲为阿湿波处刑曲 你见着阿湿波的地方都有这个</d>  
  <d p="127.39900,1,25,16777215,1513088792,0,77bddafb,4031880109">秦鹏其实我本来不想走的可是一直想你们真的好累啊。</d>  
  <d p="48.75400,1,25,16777215,1513101077,0,6a444ec7,4032285565">A叔是人吗</d>  
  <d p="190.63700,1,25,16777215,1513101217,0,6a444ec7,4032287563">音色全的不是2只手能解决的／苦笑</d>  
  <d p="187.01800,1,25,16777215,1513101751,0,414c564e,4032296114">前面一直刷存在的红色弹幕你给个av号我去看看你有多厉害？？？</d>  
  <d p="206.39100,1,25,16777215,1513101920,0,414c564e,4032296896">再舔一次我A叔的爪子wiii～</d>  
  <d p="187.18000,1,25,16777215,1513110586,0,c55d93e1,4032358317">这歌叫什么？</d>  
  <d p="207.07900,1,25,16777215,1513140784,0,84d1452b,4032707134">歌姬！！！！</d>  
  <d p="13.61800,1,25,16777215,1513156889,0,aa7e0137,4033084797">stupid Kiana</d>  
  <d p="13.61800,1,25,16707842,1513156935,0,aa7e0137,4033085884">stupid kiana happy birthday！！</d>  
  <d p="13.61800,1,25,16707842,1513156962,0,aa7e0137,4033086550">stupid kiana happy birthday！！</d>  
  <d p="179.17600,1,25,16777215,1513157546,0,7cd79721,4033100627">kiyama生日快乐！</d>  
  <d p="75.57700,1,25,16777215,1513160849,0,a4c03797,4033210105">生日快乐</d>  
  <d p="5.80600,1,25,16777215,1513245105,0,61d1a6eb,4034983067">a叔你要炸钢琴吗= = 哈哈哈哈</d>  
  <d p="11.61000,1,25,16777215,1513245123,0,61d1a6eb,4034983598">加油 咳咳我爱你 = =</d>  
  <d p="38.82500,1,25,16777215,1513245221,0,61d1a6eb,4034986538">感觉心都能沉下去= =</d>  
  <d p="59.35000,1,25,16777215,1513245274,0,61d1a6eb,4034988076">原来是这样 心如水 才能找到意义</d>  
  <d p="74.32700,1,25,16777215,1513245322,0,61d1a6eb,4034989489">好多天没来了 还是很想你们 = = 有一天 可以抱到你们</d>  
  <d p="81.36300,1,25,16777215,1513245245,0,61d1a6eb,4034990403">过程好漫长= = 努力 发烧 努力学习</d>  
  <d p="106.65000,1,25,16777215,1513245391,0,61d1a6eb,4034991495">不要太累了 = =</d>  
  <d p="129.93800,1,25,16777215,1513245365,0,61d1a6eb,4034993862">注意身体</d>  
  <d p="139.20300,1,25,16777215,1513245198,0,61d1a6eb,4034994499">真的主意身体= =</d>  
  <d p="146.21700,1,25,16777215,1513245565,0,61d1a6eb,4034996598">沉沉年年 混混噩噩 不可属实 但想要生存 = =</d>  
  <d p="161.09900,1,25,16777215,1513245575,0,61d1a6eb,4034997427">也许我不应该懒惰了 = =</d>  
  <d p="211.67300,1,25,16777215,1513245650,0,61d1a6eb,4034999135">歌姬= =</d>  
  <d p="145.40100,1,25,16777215,1513250160,0,d133cd0b,4035151376">666</d>  
  <d p="158.49500,1,25,13369446,1513250173,0,d133cd0b,4035151832">666</d>  
  <d p="31.43900,1,25,16777215,1513272486,0,b1683df9,4036017325">好好听啊</d>  
  <d p="61.41900,1,25,16777215,1513304139,0,40b24e38,4036257891">a叔是即兴的啊。。。给我一千年我也可以哦 (°ー°〃)</d>  
  <d p="142.05800,5,25,16777215,1513304266,0,40b24e38,4036259754">鱼，好大的鱼。。。</d>  
  <d p="18.50000,1,25,16777215,1513305704,0,8a6e5b33,4036286270">琪亚娜公主生日快乐</d>  
  <d p="132.34000,1,25,16777215,1513313027,0,14493ce2,4036480322">这个是雪狼联机最后一个打阿湿婆的时候的背景音乐。</d>  
  <d p="209.16600,1,25,16777215,1513313932,0,fb2c7d3d,4036521770">崩坏世界的歌姬</d>  
  <d p="180.20000,1,25,16777215,1513324449,0,456b6b01,4036780744">kiana生日快乐</d>  
  <d p="55.06700,1,25,16777215,1513331247,0,d0643c68,4036969657">kiana生日快乐</d>  
  <d p="193.68300,1,25,16777215,1513331319,0,3ff3c436,4036972836">超好听啊 励志要把钢琴学好</d>  
  <d p="121.74000,1,25,16707842,1513345217,0,f6c1cbe4,4037569426">哇这段怀孕了</d>  
  <d p="185.26100,1,25,16707842,1513345397,0,f6c1cbe4,4037573139">kiyama的退群吧</d>  
  <d p="60.79000,1,25,16777215,1513358816,0,ddd14720,4038170105">音乐有一种震撼人心的能力</d>  
  <d p="196.60800,5,25,15138834,1513359478,0,153d643d,4038188359">前方高能！注意，这不是演习！！</d>  
  <d p="29.32200,1,25,16777215,1513383077,0,c5f716ad,4038384070">阿湿波受死吧！</d>  
  <d p="6.05100,1,25,16777215,1513388558,0,888eed16,4038486729">救母</d>  
  <d p="179.24800,1,25,16777215,1513401164,0,859e38c2,4038929847">白毛生日快乐</d>  
  <d p="209.71800,1,25,16777215,1513401189,0,859e38c2,4038931000">啊啊啊啊啊啊啊啊</d>  
  <d p="224.66600,1,25,16777215,1513401204,0,859e38c2,4038931663">德莉莎世界第一可爱</d>  
  <d p="34.13900,1,25,16777215,1513416150,0,c6754a05,4039542607">琪亚娜生日快乐</d>  
  <d p="79.31900,1,25,16777215,1513416195,0,c6754a05,4039544502">是不是有延迟</d>  
  <d p="50.92200,1,25,16777215,1513434192,0,c74fe26e,4040475418">琪亚娜生日快乐！！！！</d>  
  <d p="119.29300,1,25,16777215,1513438323,0,14a9b902,4040713908">是B站压音频太狠了...</d>  
  <d p="36.12300,1,25,16777215,1513449613,0,6d3a6df8,4041114592">这个网易云会有吗？好想下啊</d>  
  <d p="44.82100,1,25,16777215,1513481424,0,8841666b,4041634267">kiana生日快乐</d>  
  <d p="11.63300,1,25,10066431,1513498406,0,79692e41,4042410615">Kiana生快!</d>  
  <d p="211.54100,1,25,16777215,1513518252,0,4633aa8e,4043276443">啊啊啊啊啊啊啊啊啊</d>  
  <d p="182.14100,1,25,16777215,1513555122,0,3b77a07c,4043994427">妈呀 太好听了</d>  
  <d p="103.40700,1,25,16711935,1513579482,0,85fb8b1c,4044469692">kiana酱生日快乐！！！！！</d>  
  <d p="68.00000,1,25,16777215,1513610412,0,1a553db4,4045490419">许愿启明星的指引</d>  
  <d p="33.34100,1,25,16777215,1513662438,0,6439d9e9,4046239372">大号许愿月光</d>  
  <d p="107.88400,1,25,16777215,1513833671,0,4f823da,4049831435">琪亚娜生日快乐</d>  
  <d p="213.87200,1,25,16777215,1513852120,0,f2212615,4050331770">美哭了</d>  
  <d p="25.77100,1,25,16777215,1513945701,0,3a2e630,4052519894">为我本命樱疯狂打call～</d>  
  <d p="77.82400,1,25,16777215,1513945776,0,3a2e630,4052523346">许愿氤氲之息</d>  
  <d p="152.57600,1,25,16777215,1513945868,0,3a2e630,4052527520">为王的诞生献上礼炮</d>  
  <d p="199.93600,1,25,16777215,1513945928,0,3a2e630,4052530278">非战斗人员请撤离</d>  
  <d p="5.05600,1,25,16777215,1513963646,0,96b2b58,4053334096">草覆虫生日快乐!</d>  
  <d p="47.48100,1,25,16777215,1514008645,0,d4187cf6,4054200353">（NaCl）琪亚娜生日快乐!</d>  
  <d p="16.00000,1,25,16777215,1514011262,0,71786920,4054298639">祝我女儿生日快乐</d>  
  <d p="35.42200,1,25,16777215,1514040889,0,623dcb20,4055674370">超好听</d>  
  <d p="70.53300,1,25,16777215,1514040942,0,623dcb20,4055676352">琪亚娜</d>  
  <d p="147.00500,1,25,16777215,1514041020,0,623dcb20,4055680837">没有音乐单曲好遗憾啊</d>  
  <d p="219.19000,1,25,16777215,1514087613,0,ff25a8c6,4056782303">听哭！！！</d>  
  <d p="14.08000,1,25,16777215,1514119720,0,63c431df,4058153007">许愿月光</d>  
  <d p="10.29100,1,25,16777215,1514132618,0,8bc92425,4058772422">硬币丢了</d>  
  <d p="225.87700,1,25,16777215,1514177628,0,855d3e8d,4059400164">崩坏世界的歌姬!大爱A叔!</d>  
  <d p="105.35600,1,25,16777215,1514191469,0,de7b9fbc,4059731389">a叔玩了崩崩崩。下一步就要卖斯坦威了</d>  
  <d p="220.50200,1,25,16777215,1514200141,0,712c276a,4059991773">a叔袖子上发光了！</d>  
  <d p="70.01100,1,25,16777215,1514221282,0,99d5f160,4060874365">表白A叔！！</d>  
  <d p="183.69600,1,25,16777215,1514340794,0,e16f5ee6,4063109738">视频速度比声音慢了一点</d>  
  <d p="47.16500,1,25,16777215,1514345972,0,1289684f,4063202372">lch liebe dich Kiana</d>  
  <d p="48.04900,1,25,16777215,1514361481,0,af7cbfac,4063594169">琪亚娜生日快乐</d>  
  <d p="22.91500,1,25,16777215,1514458940,0,b7ae7120,4118995247">报到A叔~</d>  
  <d p="141.59300,1,25,16777215,1514474321,0,a113eec9,4120269977">琪亚娜生日快乐</d>  
  <d p="83.33000,1,25,16777215,1514554687,0,f4688539,4139540735">太好听了</d>  
  <d p="97.66100,1,25,16777215,1514554702,0,f4688539,4139541538">A叔，男神</d>  
  <d p="13.01900,1,25,16777215,1514556396,0,541c013b,4139636565">许愿5th</d>  
  <d p="78.08000,1,25,38979,1514628690,0,f3120111,4141869196">啊啊啊</d>  
  <d p="108.28800,1,25,38979,1514628723,0,f3120111,4141870725">啊啊啊</d>  
  <d p="168.76800,1,25,16777215,1514770597,0,8262d76c,4147122724">说卡农的退群吧</d>  
  <d p="23.96300,1,25,16777215,1514775030,0,b3e5f8da,4147321843">许愿犹大，出必还愿</d>  
  <d p="98.52400,1,25,16777215,1514901113,0,ee2d294a,4152278523">好听</d>  
  <d p="66.39900,1,25,16777215,1514951508,0,b1683df9,4153192474">白毛生快</d>  
  <d p="14.15200,1,25,16777215,1514976071,0,d39a316,4153836972">卧槽蜜汁好听</d>  
  <d p="50.00100,1,25,16777215,1514982773,0,2666331b,4154089789">许愿一个星期合出牧童短笛</d>  
  <d p="29.60500,1,25,16777215,1515130794,0,28963a15,4157392248">听得高潮</d>  
  <d p="116.95100,4,25,16711680,1515143311,0,f5c3e50f,4157729521">光 翼 展 开</d>  
  <d p="37.73900,1,25,16777215,1515148374,0,43e07a4c,4157919506">迷一样的好听</d>  
  <d p="73.38700,1,25,16777215,1515150148,0,9fbadc4c,4157989487">Kiana生快！</d>  
  <d p="48.03800,1,25,16777215,1515156016,0,aa3140d7,4158267398">单抽出奇迹</d>  
  <d p="53.58800,1,25,16777215,1515170001,0,b173820b,4159020564">鱼，好大的鱼，虎纹鲨鱼</d>  
  <d p="6.90100,1,25,16777215,1515170055,0,9c6b2ce2,4159022732">Kiana生日快乐~</d>  
  <d p="101.25100,1,25,15138834,1515208692,0,363c8292,4159640175">6666</d>  
  <d p="32.33800,1,25,16777215,1515227072,0,d64a6512,4160445752">许愿次元边界突破，抽到定来还愿</d>  
  <d p="164.15800,1,25,16777215,1515228558,0,5edf0fc7,4160511926">为了世上的一切美好而战！</d>  
  <d p="23.66000,1,25,16777215,1515257658,0,6e31008e,4162104173">许愿月光</d>  
  <d p="51.50000,1,25,16777215,1515309905,0,e2d7ab15,4163626399">鱼，好大的鱼，虎纹鲨鱼</d>  
  <d p="28.93600,1,25,16777215,1515311866,0,9e955478,4163724622">残影~~</d>  
  <d p="129.04800,1,25,16777215,1515319706,0,11d46d52,4164088586">好听</d>  
  <d p="87.00000,1,25,16777215,1515323945,0,ba81eaac,4164283243">红字好评</d>  
  <d p="17.50500,1,25,13395558,1515330045,0,6cf2c960,4164590855">真帅</d>  
  <d p="108.70500,1,25,16711680,1515330136,0,6cf2c960,4164595616">贼帅</d>  
  <d p="189.36200,1,25,16777215,1515336174,0,f0e5691a,4165076600">好听</d>  
  <d p="102.47200,1,25,16777215,1515340647,0,89843831,4165319101">听得银行卡瑟瑟发抖</d>  
  <d p="19.50800,1,25,16777215,1515361178,0,ba4656a9,4165667773">草履虫</d>  
  <d p="7.31000,5,25,41194,1515411261,0,e265de0e,4166800144">琪亚娜老婆大人，生日快乐！</d>  
  <d p="36.91600,5,25,41194,1515411299,0,e265de0e,4166801774">kiana生日快乐</d>  
  <d p="89.12000,5,25,15138834,1515507668,0,1d184cb1,4169388305">厉害厉害！</d>  
  <d p="174.10200,1,25,16777215,1515509511,0,5657e49d,4169476628">K423生日快乐</d>  
  <d p="37.30100,1,25,16777215,1515557941,0,f667a2b4,4170272540">许愿月光啦啦啦啦</d>  
  <d p="64.06000,1,25,16777215,1515902457,0,6ab97e5a,4179998180">崩坏的歌现在很少听得见</d>  
  <d p="80.00000,1,25,16777215,1515986076,0,f0c65294,4182670270">听完再剁一次</d>  
  <d p="57.20900,1,25,16707842,1516034190,0,940c5419,4184442635">好喜欢这段踩的踏板！特别有感觉！！</d>  
  <d p="81.49000,1,25,16777215,1516092137,0,2a501cf0,4185496910">大伟哥才换的别墅又倒了</d>  
  <d p="0.14900,5,25,15138834,1516208602,0,9f9242fc,4189143339">（阿湿波）进入直播间</d>  
  <d p="20.04100,1,25,16777215,1516282861,0,8d05404,4190968441">这个和弦不快啊，哪来什么手速啊</d>  
  <d p="74.32500,1,25,16777215,1516355611,0,497caffc,4192989551">许愿卡莲</d>  
  <d p="40.04600,1,25,16777215,1516440999,0,46012508,4195752997">已给A叔投币子</d>  
  <d p="87.71400,1,25,16777215,1516660130,0,2a501cf0,4202811314">广电还我完整崩三</d>  
  <d p="92.23000,1,25,16777215,1516690970,0,56e5d0bd,4203555306">Kiana生快</d>  
  <d p="187.15800,1,25,16777215,1516702438,0,20dcf26,4204675723">像又怎样</d>  
  <d p="109.32000,1,25,16777215,1516854167,0,9a71907c,4211597025">跑动好流畅</d>  
  <d p="62.35000,1,25,16777215,1516988913,0,c641266e,4216794847">前面说8级的你在逗我么</d>  
  <d p="56.15100,1,25,16777215,1517026669,0,aee219ac,4217458257">可能我多长两只手就弹得过来了</d>  
  <d p="54.44500,1,25,16777215,1517196357,0,173ed2d9,4224071081">切，给我三辈子我也练的出来</d>  
  <d p="35.15800,1,25,16777215,1517233544,0,2656b381,4225712914">教练，我想学钢琴</d>  
  <d p="64.81800,1,25,16777215,1517233592,0,2656b381,4225715763">许愿月光</d>  
  <d p="93.65700,1,25,16777215,1517275121,0,321f0b5,4231120051">妈！多给我长两只手可以？？？</d>  
  <d p="31.92000,5,25,15138834,1517365846,0,f4688539,4234237738">大爱a叔</d>  
  <d p="171.70700,1,25,16777215,1517365934,0,d911c702,4234240430">这要做成谱子要弹的起来7级不能再低了</d>  
  <d p="199.32300,1,25,16777215,1517549462,0,6b4a9874,4246623647">唉，现在崩3不能摸了</d>  
  <d p="59.86100,1,25,16777215,1517727071,0,ac21f151,4253429445">燃爆了</d>  
  <d p="75.86300,1,25,16777215,1517816746,0,9b23f4a0,4257077475">A叔祝我抽到八重樱啊啊啊啊</d>  
  <d p="151.76100,1,25,16776960,1517838769,0,ec1c821e,4258303647">A叔瘦了</d>  
  <d p="9.50500,1,25,16777215,1518060272,0,6ef25218,4274812901">666</d>  
  <d p="157.54700,1,25,16777215,1518060474,0,6ef25218,4274822220">好想存手机里听</d>  
  <d p="211.39800,1,25,16777215,1518060621,0,6ef25218,4274828902">鸡皮疙瘩！</d>  
  <d p="5.34200,1,25,16777215,1518249593,0,52571c24,4283133589">感动</d>  
  <d p="23.14200,1,25,16777215,1518423946,0,55e63114,4290804688">模糊</d>  
  <d p="94.97500,1,25,16777215,1518444057,0,a4fa1e05,4292008457">琪亚娜生日快乐</d>  
  <d p="97.35000,1,25,16777215,1518457424,0,372d0d53,4292812970">琪亚娜生日快乐</d>  
  <d p="124.69800,1,25,16777215,1518490022,0,b12e2288,4293419622">阿湿波，可能刚六十级的记忆深刻些</d>  
  <d p="31.18100,1,25,16777215,1518522004,0,af7ebde3,4295147263">新年快乐</d>  
  <d p="62.95900,1,25,16777215,1518831738,0,52571c24,4309562688">我大崩坏</d>  
  <d p="8.18000,1,25,16777215,1519016505,0,288b0a56,4317449986">琪亚娜 出击</d>  
  <d p="153.53700,4,25,16777215,1519022954,0,e065b6e0,4317791138">光</d>  
  <d p="153.53700,4,25,16777215,1519022964,0,e065b6e0,4317791706">翼</d>  
  <d p="153.53700,4,25,16777215,1519022982,0,e065b6e0,4317792640">展</d>  
  <d p="153.53700,4,25,16777215,1519022992,0,e065b6e0,4317793216">开！！！</d>  
  <d p="153.53700,4,25,16777215,1519023011,0,e065b6e0,4317794126">（月光白）</d>  
  <d p="216.11700,1,25,16777215,1519112196,0,8fda79a,4323351260">歌姬</d>  
  <d p="71.32300,1,25,16777215,1519464571,0,24db35a8,4339408875">琪亚娜生日快乐</d>  
  <d p="216.83400,1,25,16777215,1519657953,0,1fd860ab,4347227348">格里芬指挥官祝琪亚娜生日快乐</d>  
  <d p="221.78400,1,25,16777215,1519951643,0,f171a1ac,4356955524">👍</d>  
  <d p="205.03400,1,25,16777215,1520002513,0,870bfad0,4359543570">温情</d>  
  <d p="215.15000,1,25,16777215,1520002523,0,870bfad0,4359544187">崩坏3</d>  
  <d p="22.31200,1,25,16777215,1520014452,0,98d5bd1f,4360102170">琪亚娜生日快乐</d>  
  <d p="52.95100,1,25,16777215,1520067551,0,e8107665,4361681405">许愿月光</d>  
  <d p="0.08300,1,25,16777215,1520153122,0,9b892695,4365042913">啊啊啊！！！帅帅帅</d>  
  <d p="66.08100,1,25,16777215,1520232714,0,f187d74d,4367200994">愿我早日甘出来月光吧，让我抽到一次S人物啊，还一次愿行吗</d>  
  <d p="208.74400,1,25,16777215,1520253408,0,a712b68c,4367794861">崩坏世界的歌姬！怀念崩坏2</d>  
  <d p="74.22300,1,25,16777215,1520351550,0,14c1ae91,4370501899">too late happy brithday</d>  
  <d p="100.96100,1,25,16777215,1520489170,0,7047b1b1,4373014596">琪安娜生日快乐</d>  
  <d p="29.78100,1,25,16777215,1520739779,0,3c50f01a,4379996492">真的，音画不同步啊</d>  
  <d p="222.42600,1,25,16777215,1520913582,0,ccea4a7,4384545885">崩坏世界的歌姬</d>  
  <d p="66.00400,1,25,16777215,1521089341,0,4f7ec9ae,4388366083">打破1000条弹幕</d>  
  <d p="4.75900,1,25,16777215,1521179476,0,de0b6988,4390442417">又来了</d>  
  <d p="0.87200,1,25,16777215,1521457366,0,6fbe0e1d,4398815160">什么时候能在摸摸琪亚娜</d>  
  <d p="75.93900,1,25,16777215,1521791540,0,8a84f3b2,4406274616">嘁，真辣鸡，给我1000年我也会</d>  
  <d p="91.43800,5,25,15138834,1521901276,0,d552b320,4410073723">好听，有种孤寂的感觉</d>  
  <d p="51.97400,1,25,16777215,1522481204,0,d3d626d9,4425100532">Happy birthday Kiana!</d>  
  <d p="114.36000,1,25,16777215,1522899769,0,e0090c2c,4436902785">许愿炽翎，出必还原</d>  
  <d p="12.28100,1,25,16777215,1522936954,0,2f971ef3,4438773312">七日之都【滑稽】</d>  
  <d p="40.92100,1,25,16777215,1522937002,0,2f971ef3,4438776358">永远的七日之都《滑稽》</d>  
  <d p="33.00000,1,25,5141359,1522941447,0,55929b6c,4439050941">许愿月光</d>  
  <d p="61.00000,1,25,16777215,1522941475,0,55929b6c,4439052523">许愿月光</d>  
  <d p="47.73700,1,25,16777215,1523112576,0,8ef4d031,4445317482">:)</d>  
  <d p="34.39600,1,25,16777215,1523184973,0,322b5cd3,4446942966">琪亚娜生日快乐</d>  
  <d p="11.20000,1,25,16777215,1523283345,0,5bf1b91f,4449458773">布洛尼亚</d>  
  <d p="75.43200,1,25,16777215,1523366368,0,37e84567,4451455184">琪亚娜生日快乐！</d>  
  <d p="17.81900,1,25,16777215,1523459663,0,67048340,4453734062">我要抽月光或者鬼铠，出货后必来还愿</d>  
  <d p="53.76700,1,25,16777215,1523468888,0,8badde1f,4454002733">kiana生日快乐～</d>  
  <d p="17.06800,1,25,16777215,1523495895,0,63250fb4,4454213234">注入灵魂</d>  
  <d p="181.53600,1,25,16777215,1523533157,0,a728235e,4455136178">全程残影</d>  
  <d p="179.00300,1,25,16777215,1523551275,0,e39f55d7,4455940045">七级？我业十的看着压力山大？</d>  
  <d p="84.66800,1,25,16777215,1523833173,0,9cf2b432,4464482353">表白字幕~</d>  
  <d p="102.54200,4,25,38979,1523852063,0,2c548c51,4464782646">字幕君辛苦啦</d>  
  <d p="19.86000,1,25,13382400,1524482550,0,ebe3cc1f,4482321943">厉害</d>  
  <d p="36.11300,1,25,16777215,1524656856,0,10329f87,4486505738">鬼铠，月光</d>  
  <d p="120.02400,5,25,10092543,1524656940,0,10329f87,4486508790">白骑士，影骑士随便一个有一个就满足了</d>  
  <d p="155.51200,5,25,10092543,1524656975,0,10329f87,4486517048">不奢求多的S级，有了月光就满足了，可惜没有</d>  
  <d p="40.72000,1,25,16777215,1524669354,0,33b94ef4,4487107132">琪亚娜生日快乐</d>  
  <d p="75.91000,1,25,16777215,1525256455,0,dcf99d51,4505500164">许愿鬼铠</d>  
  <d p="104.62600,5,25,10053324,1525256484,0,dcf99d51,4505501236">许愿鬼铠</d>  
  <d p="116.33200,1,25,16777215,1525304668,0,b3940081,4506775717">许愿白骑士月光</d>  
  <d p="62.39300,1,25,16777215,1525338476,0,f794e845,4507502461">钢琴版比原版火系列</d>  
  <d p="22.74700,1,25,16777215,1525440381,0,7b7d32a8,4510580120">许愿新卡莲</d>  
  <d p="214.76600,1,25,16777215,1525574005,0,34549aaa,4515303514">歌姬！！！</d>  
  <d p="96.72300,1,25,16777215,1525689273,0,63250fb4,4519113840">越听越有力量</d>  
  <d p="95.68200,1,25,16777215,1525818793,0,aedea930,4522608617">琪亚娜生日快乐</d>  
  <d p="62.12000,1,25,16777215,1525962505,0,2673d02d,4526468807">琪亚娜生日快乐</d>  
  <d p="212.00000,1,25,16777215,1525962682,0,2673d02d,4526477822">崩坏世界的歌姬！</d>  
  <d p="156.24900,1,25,16777215,1526138799,0,81c7fb15,4532264044">琪亚娜生日快乐</d>  
  <d p="31.82900,1,25,16777215,1526145479,0,3c7d6a12,4532584246">kiana生日快乐！</d>  
  <d p="54.88100,1,25,16777215,1526182098,0,20c5c068,4533356846">弹错了…等等这是谁？抱歉，打扰了</d>  
  <d p="134.62200,1,25,16777215,1526183589,0,cbc0b7be,4533427097">A叔是演奏级的，8级是这曲子的级别，你看他别的曲</d>  
  <d p="166.63400,1,25,16777215,1526263595,0,56e6879,4535971167">雷电，炸裂吧！</d>  
  <d p="210.92800,1,25,16777215,1526263639,0,56e6879,4535971880">突然接歌姬！</d>  
  <d p="99.67800,1,25,16777215,1526297387,0,d070ec12,4536931679">大伟这是下了血本了</d>  
  <d p="24.91900,1,25,16777215,1526309332,0,7cf2a45e,4537475824">Kiana生日快乐</d>  
  <d p="200.26000,1,25,16777215,1526309522,0,7cf2a45e,4537485481">崩坏世界的歌姬！！！</d>  
  <d p="120.81600,5,25,8700107,1526387251,0,93e8b9ab,4539151045">对不起，月光月轮都有，月光ss↑</d>  
  <d p="173.44600,5,25,16707842,1526387374,0,93e8b9ab,4539156036">上面别胡乱表白阿，这是德语的“我爱你”阿。。↑</d>  
  <d p="114.20000,1,25,16777215,1527033793,0,c7b59c7e,4557271946">我要月光</d>  
  <d p="169.36000,1,25,16777215,1527033863,0,c7b59c7e,4557272614">前面说卡农的是个什么鬼</d>  
  <d p="105.83800,1,25,9487136,1527275359,0,9fe87cbb,69826886238210">日服的表示不知</d> 
</i>
